[{"ci":"422406","ri":"422407","ti":"422409","tc":"Буэнос Айрес","wi":29.8,"pi":"1526","mi":"E","v":50087,"sc":12,"cc":11,"lpe":60.73,"lpr":35794.39,"lq":6.6,"spr":66264.64,"sq":8.39,"sb":1.33},{"ci":"422406","ri":"422407","ti":"422414","tc":"Ла-Плата","wi":22.73,"pi":"1526","mi":"E","v":2336,"sc":4,"cc":3,"lpe":68.07,"lpr":19844.59,"lq":3.36,"spr":45113.33,"sq":5.62,"sb":1.28},{"ci":"422406","ri":"422407","ti":"422415","tc":"Мар-дель-Плата","wi":16.55,"pi":"1526","mi":"E","v":944,"sc":6,"cc":2,"lpe":73.52,"lpr":34404.31,"lq":5.51,"spr":67309.17,"sq":6.29,"sb":1.04},{"ci":"422406","ri":"422407","ti":"422411","tc":"Росарио","wi":22.7,"pi":"1526","mi":"E","v":3853,"sc":10,"cc":5,"lpe":72.33,"lpr":22527.4,"lq":4.22,"spr":47627.69,"sq":5.99,"sb":0.87},{"ci":"422406","ri":"422407","ti":"422417","tc":"Санта-Фе","wi":10.39,"pi":"1526","mi":"E","v":944,"sc":8,"cc":2,"lpe":87.82,"lpr":24558.93,"lq":4.12,"spr":39203.58,"sq":4.63,"sb":0.45},{"ci":"422406","ri":"422408","ti":"422410","tc":"Кордова","wi":15.69,"pi":"1526","mi":"E","v":3804,"sc":4,"cc":4,"lpe":78.79,"lpr":16517.0,"lq":3.31,"spr":34030.89,"sq":4.99,"sb":0.85},{"ci":"422406","ri":"422408","ti":"422412","tc":"Мендоса","wi":15.35,"pi":"1526","mi":"E","v":3350,"sc":2,"cc":2,"lpe":80.51,"lpr":40037.43,"lq":5.87,"spr":66334.01,"sq":6.55,"sb":0.78},{"ci":"422406","ri":"422408","ti":"422416","tc":"Сальта","wi":12.69,"pi":"1526","mi":"D","v":284,"sc":3,"cc":3,"lpe":35.56,"lpr":144132.12,"lq":3.51,"spr":157690.95,"sq":4.45,"sb":0.01},{"ci":"422406","ri":"422408","ti":"422413","tc":"Сан-Мигель-де-Тукуман","wi":16.45,"pi":"1526","mi":"E","v":2381,"sc":3,"cc":3,"lpe":69.0,"lpr":35007.78,"lq":6.08,"spr":63972.19,"sq":6.94,"sb":0.71},{"ci":"422406","ri":"422408","ti":"422418","tc":"Сан-Хуан","wi":10.65,"pi":"1526","mi":"","v":291,"sc":0,"cc":0,"lpe":100.0,"lpr":179494.75,"lq":1.0,"spr":179494.75,"sq":1.0,"sb":0.0},{"ci":"15904","ri":"15916","ti":"15936","tc":"Бирмингем","wi":19.74,"pi":"1526","mi":"E","v":18458,"sc":6,"cc":6,"lpe":84.58,"lpr":22448.82,"lq":3.92,"spr":34401.12,"sq":4.85,"sb":0.61},{"ci":"15904","ri":"15916","ti":"352886","tc":"Бристоль","wi":13.55,"pi":"1526","mi":"E","v":2157,"sc":1,"cc":1,"lpe":86.09,"lpr":32445.48,"lq":4.87,"spr":46708.97,"sq":5.6,"sb":0.59},{"ci":"15904","ri":"15916","ti":"15944","tc":"Кингстон","wi":15.63,"pi":"1526","mi":"E","v":1076,"sc":4,"cc":1,"lpe":93.68,"lpr":39207.83,"lq":1.0,"spr":42687.26,"sq":1.28,"sb":0.02},{"ci":"15904","ri":"15916","ti":"15943","tc":"Ковентри","wi":14.72,"pi":"1526","mi":"E","v":405,"sc":1,"cc":1,"lpe":75.31,"lpr":44408.8,"lq":5.43,"spr":55665.89,"sq":5.9,"sb":0.5},{"ci":"15904","ri":"15916","ti":"15942","tc":"Лестер","wi":13.44,"pi":"1526","mi":"E","v":564,"sc":2,"cc":2,"lpe":90.25,"lpr":35685.85,"lq":4.72,"spr":43498.23,"sq":4.87,"sb":0.01},{"ci":"15904","ri":"15916","ti":"373539","tc":"Ливерпуль","wi":19.45,"pi":"1526","mi":"E","v":2028,"sc":2,"cc":2,"lpe":81.16,"lpr":47963.01,"lq":8.0,"spr":74633.57,"sq":8.64,"sb":0.82},{"ci":"15904","ri":"15916","ti":"15938","tc":"Лидс","wi":17.18,"pi":"1526","mi":"E","v":5465,"sc":3,"cc":3,"lpe":79.98,"lpr":23524.13,"lq":4.33,"spr":46192.48,"sq":5.75,"sb":0.86},{"ci":"15904","ri":"15916","ti":"15935","tc":"Лондон","wi":24.24,"pi":"1526","mi":"E","v":67430,"sc":13,"cc":11,"lpe":70.94,"lpr":32194.45,"lq":5.42,"spr":54454.63,"sq":6.78,"sb":1.06},{"ci":"15904","ri":"15916","ti":"15941","tc":"Манчестер","wi":19.41,"pi":"1526","mi":"E","v":18534,"sc":5,"cc":5,"lpe":75.63,"lpr":27562.41,"lq":4.62,"spr":49264.55,"sq":6.18,"sb":0.7},{"ci":"15904","ri":"15916","ti":"348029","tc":"Шеффилд","wi":21.14,"pi":"1526","mi":"E","v":2346,"sc":4,"cc":4,"lpe":81.54,"lpr":17020.01,"lq":3.11,"spr":38300.82,"sq":4.6,"sb":0.79},{"ci":"15904","ri":"15919","ti":"15951","tc":"Белфаст","wi":8.71,"pi":"1526","mi":"E","v":700,"sc":2,"cc":2,"lpe":80.57,"lpr":38420.84,"lq":4.68,"spr":48329.05,"sq":4.74,"sb":0.43},{"ci":"15904","ri":"15919","ti":"15952","tc":"Дерри","wi":8.67,"pi":"1526","mi":"D","v":181,"sc":2,"cc":2,"lpe":41.44,"lpr":11180.43,"lq":1.94,"spr":20069.24,"sq":4.32,"sb":0.13},{"ci":"15904","ri":"15919","ti":"15953","tc":"Лисберн","wi":15.8,"pi":"1526","mi":"E","v":490,"sc":1,"cc":1,"lpe":98.78,"lpr":65792.23,"lq":1.0,"spr":65770.28,"sq":1.04,"sb":0.0},{"ci":"15904","ri":"15918","ti":"15948","tc":"Кардифф","wi":16.29,"pi":"1526","mi":"E","v":1889,"sc":2,"cc":2,"lpe":85.6,"lpr":20690.3,"lq":4.03,"spr":37765.52,"sq":4.98,"sb":0.85},{"ci":"15904","ri":"15918","ti":"15950","tc":"Ньюпорт","wi":10.6,"pi":"1526","mi":"E","v":153,"sc":1,"cc":1,"lpe":94.77,"lpr":30197.83,"lq":1.0,"spr":43677.68,"sq":1.38,"sb":0.21},{"ci":"15904","ri":"15918","ti":"15949","tc":"Суонси","wi":13.07,"pi":"1526","mi":"E","v":189,"sc":1,"cc":1,"lpe":92.59,"lpr":80760.25,"lq":2.72,"spr":81000.23,"sq":2.85,"sb":0.0},{"ci":"15904","ri":"15917","ti":"15947","tc":"Абердин","wi":13.72,"pi":"1526","mi":"E","v":276,"sc":1,"cc":1,"lpe":98.91,"lpr":23828.55,"lq":3.32,"spr":25254.33,"sq":3.4,"sb":0.05},{"ci":"15904","ri":"15917","ti":"15945","tc":"Глазго","wi":17.53,"pi":"1526","mi":"E","v":2258,"sc":4,"cc":4,"lpe":76.66,"lpr":26086.7,"lq":5.78,"spr":57000.27,"sq":6.99,"sb":1.11},{"ci":"15904","ri":"15917","ti":"15946","tc":"Эдинбург","wi":25.25,"pi":"1526","mi":"E","v":2595,"sc":4,"cc":4,"lpe":77.76,"lpr":20635.5,"lq":4.08,"spr":46294.66,"sq":5.61,"sb":1.03},{"ci":"375142","ri":"375143","ti":"375147","tc":"Баркисимето","wi":13.82,"pi":"1526","mi":"E","v":4690,"sc":2,"cc":2,"lpe":89.21,"lpr":30451.05,"lq":5.12,"spr":39596.27,"sq":5.65,"sb":0.42},{"ci":"375142","ri":"375143","ti":"375151","tc":"Барселона (Ve)","wi":8.42,"pi":"1526","mi":"E","v":257,"sc":1,"cc":1,"lpe":93.39,"lpr":29206.15,"lq":1.07,"spr":37664.99,"sq":1.53,"sb":0.1},{"ci":"375142","ri":"375143","ti":"375146","tc":"Валенсия (Ve)","wi":14.14,"pi":"1526","mi":"E","v":6679,"sc":4,"cc":4,"lpe":85.22,"lpr":27067.25,"lq":4.67,"spr":40877.2,"sq":5.34,"sb":0.44},{"ci":"375142","ri":"375143","ti":"375144","tc":"Каракас","wi":20.19,"pi":"1526","mi":"E","v":16037,"sc":9,"cc":8,"lpe":74.48,"lpr":29906.83,"lq":5.14,"spr":49952.96,"sq":6.47,"sb":0.52},{"ci":"375142","ri":"375143","ti":"375149","tc":"Маракай","wi":8.14,"pi":"1526","mi":"E","v":319,"sc":2,"cc":2,"lpe":70.85,"lpr":22057.56,"lq":3.68,"spr":36519.54,"sq":4.44,"sb":0.08},{"ci":"375142","ri":"375143","ti":"375145","tc":"Маракайбо","wi":19.82,"pi":"1526","mi":"E","v":13661,"sc":5,"cc":5,"lpe":77.37,"lpr":38915.91,"lq":6.42,"spr":60916.32,"sq":7.38,"sb":0.45},{"ci":"375142","ri":"375143","ti":"375150","tc":"Матурин","wi":8.05,"pi":"1526","mi":"","v":714,"sc":0,"cc":0,"lpe":100.0,"lpr":51267.75,"lq":1.0,"spr":51267.75,"sq":1.0,"sb":0.0},{"ci":"375142","ri":"375143","ti":"375148","tc":"Сьюдад-Гуаяна","wi":14.95,"pi":"1526","mi":"D","v":2696,"sc":3,"cc":3,"lpe":48.81,"lpr":33008.08,"lq":4.57,"spr":42664.55,"sq":4.62,"sb":0.03},{"ci":"15912","ri":"15931","ti":"15989","tc":"Канкан","wi":7.03,"pi":"1526","mi":"E","v":98,"sc":2,"cc":2,"lpe":78.57,"lpr":30477.35,"lq":4.34,"spr":55345.76,"sq":5.5,"sb":0.71},{"ci":"15912","ri":"15931","ti":"15988","tc":"Конакри","wi":2.82,"pi":"1526","mi":"E","v":4516,"sc":1,"cc":1,"lpe":81.44,"lpr":9008.98,"lq":1.49,"spr":17357.62,"sq":3.47,"sb":0.78},{"ci":"15912","ri":"15931","ti":"15990","tc":"Нзерекоре","wi":5.24,"pi":"1526","mi":"E","v":568,"sc":2,"cc":2,"lpe":62.5,"lpr":25443.65,"lq":4.91,"spr":40156.9,"sq":7.21,"sb":1.57},{"ci":"15905","ri":"15921","ti":"3043","tc":"Берлин","wi":16.87,"pi":"1526","mi":"E","v":30582,"sc":10,"cc":5,"lpe":76.9,"lpr":12352.79,"lq":2.03,"spr":22827.46,"sq":3.56,"sb":0.89},{"ci":"15905","ri":"15921","ti":"15957","tc":"Дрезден","wi":16.2,"pi":"1526","mi":"E","v":3380,"sc":4,"cc":4,"lpe":83.11,"lpr":13567.61,"lq":2.45,"spr":26663.27,"sq":4.01,"sb":0.69},{"ci":"15905","ri":"15921","ti":"15956","tc":"Лейпциг","wi":16.2,"pi":"1526","mi":"E","v":1828,"sc":3,"cc":3,"lpe":66.47,"lpr":13154.88,"lq":4.12,"spr":34974.99,"sq":6.36,"sb":1.14},{"ci":"15905","ri":"15920","ti":"15955","tc":"Бонн","wi":27.13,"pi":"1526","mi":"E","v":2942,"sc":3,"cc":3,"lpe":82.9,"lpr":57916.15,"lq":8.13,"spr":82313.85,"sq":8.67,"sb":0.78},{"ci":"15905","ri":"15920","ti":"3052","tc":"Бремен","wi":24.73,"pi":"1526","mi":"E","v":2777,"sc":3,"cc":3,"lpe":79.29,"lpr":47713.79,"lq":7.88,"spr":80675.39,"sq":8.43,"sb":0.91},{"ci":"15905","ri":"15920","ti":"3044","tc":"Гамбург","wi":26.64,"pi":"1526","mi":"E","v":15667,"sc":7,"cc":7,"lpe":73.4,"lpr":13781.88,"lq":2.39,"spr":31122.75,"sq":4.49,"sb":1.0},{"ci":"15905","ri":"15920","ti":"3053","tc":"Ганновер","wi":27.81,"pi":"1526","mi":"E","v":2449,"sc":3,"cc":3,"lpe":75.01,"lpr":66076.24,"lq":7.6,"spr":104224.29,"sq":8.28,"sb":0.92},{"ci":"15905","ri":"15920","ti":"3049","tc":"Дортмунд","wi":23.94,"pi":"1526","mi":"E","v":2775,"sc":3,"cc":3,"lpe":79.89,"lpr":46504.09,"lq":7.89,"spr":75436.13,"sq":8.58,"sb":0.92},{"ci":"15905","ri":"15920","ti":"3051","tc":"Дюссельдорф","wi":24.58,"pi":"1526","mi":"E","v":3870,"sc":3,"cc":3,"lpe":79.69,"lpr":59580.56,"lq":7.97,"spr":92335.14,"sq":8.66,"sb":0.93},{"ci":"15905","ri":"15920","ti":"3046","tc":"Кёльн","wi":23.05,"pi":"1526","mi":"E","v":8464,"sc":5,"cc":5,"lpe":77.52,"lpr":51563.54,"lq":7.47,"spr":73493.98,"sq":8.16,"sb":0.96},{"ci":"15905","ri":"15920","ti":"3045","tc":"Мюнхен","wi":22.94,"pi":"1526","mi":"E","v":7999,"sc":5,"cc":5,"lpe":67.68,"lpr":46522.86,"lq":6.74,"spr":76532.98,"sq":7.37,"sb":1.24},{"ci":"15905","ri":"15920","ti":"15954","tc":"Нюрнберг","wi":24.43,"pi":"1526","mi":"E","v":4360,"sc":4,"cc":4,"lpe":79.36,"lpr":51717.55,"lq":7.78,"spr":76175.54,"sq":8.42,"sb":0.87},{"ci":"15905","ri":"15920","ti":"3047","tc":"Франкфурт","wi":31.83,"pi":"1526","mi":"E","v":5350,"sc":4,"cc":4,"lpe":81.03,"lpr":56093.93,"lq":7.96,"spr":82571.7,"sq":8.58,"sb":0.84},{"ci":"15905","ri":"15920","ti":"3050","tc":"Штутгарт","wi":25.63,"pi":"1526","mi":"E","v":3020,"sc":4,"cc":4,"lpe":76.99,"lpr":77809.18,"lq":8.8,"spr":111530.08,"sq":9.32,"sb":1.02},{"ci":"15905","ri":"15920","ti":"3048","tc":"Эссен","wi":24.48,"pi":"1526","mi":"E","v":4355,"sc":4,"cc":4,"lpe":82.5,"lpr":13623.9,"lq":2.57,"spr":28251.0,"sq":4.11,"sb":0.8},{"ci":"422043","ri":"422044","ti":"422046","tc":"Афины","wi":21.39,"pi":"1526","mi":"E","v":14230,"sc":9,"cc":9,"lpe":67.18,"lpr":59540.4,"lq":8.58,"spr":76116.08,"sq":9.0,"sb":1.01},{"ci":"422043","ri":"422044","ti":"422051","tc":"Волос","wi":7.66,"pi":"1526","mi":"E","v":448,"sc":3,"cc":3,"lpe":80.58,"lpr":17072.3,"lq":2.87,"spr":27522.55,"sq":3.83,"sb":0.14},{"ci":"422043","ri":"422044","ti":"422050","tc":"Ларисса","wi":8.63,"pi":"1526","mi":"E","v":99,"sc":1,"cc":1,"lpe":63.64,"lpr":34512.39,"lq":5.68,"spr":58326.07,"sq":6.72,"sb":0.12},{"ci":"422043","ri":"422044","ti":"422495","tc":"Пирей","wi":9.49,"pi":"1526","mi":"E","v":548,"sc":2,"cc":2,"lpe":86.68,"lpr":23836.64,"lq":4.02,"spr":30070.08,"sq":4.37,"sb":0.0},{"ci":"422043","ri":"422044","ti":"422047","tc":"Салоники","wi":15.36,"pi":"1526","mi":"E","v":1420,"sc":3,"cc":3,"lpe":65.0,"lpr":84518.19,"lq":9.06,"spr":121181.46,"sq":9.61,"sb":1.46},{"ci":"422043","ri":"422044","ti":"423002","tc":"Янина","wi":17.37,"pi":"1526","mi":"E","v":337,"sc":1,"cc":1,"lpe":98.52,"lpr":67011.58,"lq":1.0,"spr":67026.24,"sq":1.04,"sb":0.0},{"ci":"422043","ri":"422045","ti":"422049","tc":"Ираклион","wi":7.32,"pi":"1526","mi":"E","v":100,"sc":2,"cc":2,"lpe":78.0,"lpr":34047.34,"lq":5.71,"spr":62189.09,"sq":6.86,"sb":0.09},{"ci":"422043","ri":"422045","ti":"422048","tc":"Патры","wi":7.81,"pi":"1526","mi":"D","v":147,"sc":3,"cc":3,"lpe":41.5,"lpr":44096.9,"lq":5.63,"spr":59732.66,"sq":5.96,"sb":0.1},{"ci":"422043","ri":"422045","ti":"422997","tc":"Родос","wi":8.84,"pi":"1526","mi":"E","v":292,"sc":1,"cc":1,"lpe":90.41,"lpr":21724.72,"lq":2.32,"spr":26353.86,"sq":2.49,"sb":0.0},{"ci":"422043","ri":"422045","ti":"422052","tc":"Ханья","wi":6.75,"pi":"1526","mi":"E","v":95,"sc":1,"cc":1,"lpe":91.58,"lpr":36532.14,"lq":4.23,"spr":44569.51,"sq":4.51,"sb":0.2},{"ci":"17597","ri":"17598","ti":"17600","tc":"Барселона","wi":17.72,"pi":"1526","mi":"E","v":12139,"sc":9,"cc":9,"lpe":83.89,"lpr":15379.53,"lq":2.69,"spr":28145.35,"sq":4.08,"sb":0.69},{"ci":"17597","ri":"17598","ti":"17608","tc":"Бильбао","wi":14.25,"pi":"1526","mi":"E","v":2668,"sc":3,"cc":3,"lpe":98.73,"lpr":48533.98,"lq":1.0,"spr":50491.32,"sq":1.13,"sb":0.01},{"ci":"17597","ri":"17598","ti":"17601","tc":"Валенсия","wi":18.51,"pi":"1526","mi":"E","v":5406,"sc":4,"cc":4,"lpe":78.08,"lpr":39999.99,"lq":6.71,"spr":69116.11,"sq":7.58,"sb":0.93},{"ci":"17597","ri":"17598","ti":"17606","tc":"Лас-Пальмас-де-Гран-Канария","wi":25.15,"pi":"1526","mi":"E","v":1902,"sc":4,"cc":4,"lpe":70.24,"lpr":15628.96,"lq":3.19,"spr":35390.4,"sq":5.29,"sb":0.67},{"ci":"17597","ri":"17598","ti":"17599","tc":"Мадрид","wi":24.67,"pi":"1526","mi":"E","v":25386,"sc":6,"cc":6,"lpe":81.76,"lpr":13783.86,"lq":2.62,"spr":26204.74,"sq":4.03,"sb":0.82},{"ci":"17597","ri":"17598","ti":"17604","tc":"Малага","wi":15.75,"pi":"1526","mi":"E","v":4760,"sc":3,"cc":3,"lpe":87.71,"lpr":10178.69,"lq":1.75,"spr":19854.26,"sq":3.01,"sb":0.54},{"ci":"17597","ri":"17598","ti":"17605","tc":"Мурсия","wi":12.28,"pi":"1526","mi":"E","v":3269,"sc":5,"cc":5,"lpe":75.65,"lpr":31408.57,"lq":5.37,"spr":48575.53,"sq":6.1,"sb":0.78},{"ci":"17597","ri":"17598","ti":"17607","tc":"Пальма-де-Майорка","wi":21.97,"pi":"1526","mi":"E","v":2158,"sc":3,"cc":3,"lpe":83.92,"lpr":17382.86,"lq":3.85,"spr":35355.67,"sq":5.04,"sb":0.73},{"ci":"17597","ri":"17598","ti":"423034","tc":"Сантандер","wi":32.42,"pi":"1526","mi":"E","v":688,"sc":3,"cc":3,"lpe":72.67,"lpr":26735.65,"lq":4.08,"spr":48194.51,"sq":4.9,"sb":0.77},{"ci":"17597","ri":"17598","ti":"17603","tc":"Сарагоса","wi":25.14,"pi":"1526","mi":"E","v":2287,"sc":5,"cc":5,"lpe":75.03,"lpr":19023.73,"lq":4.82,"spr":43384.24,"sq":6.38,"sb":1.14},{"ci":"17597","ri":"17598","ti":"17602","tc":"Севилья","wi":20.26,"pi":"1526","mi":"E","v":4300,"sc":4,"cc":4,"lpe":80.7,"lpr":11362.68,"lq":2.07,"spr":26235.37,"sq":3.79,"sb":0.89},{"ci":"15915","ri":"15934","ti":"16001","tc":"Абиджан","wi":6.75,"pi":"1526","mi":"D","v":9341,"sc":4,"cc":4,"lpe":30.55,"lpr":36871.53,"lq":3.27,"spr":34539.38,"sq":5.13,"sb":0.17},{"ci":"15915","ri":"15934","ti":"16002","tc":"Буаке","wi":4.27,"pi":"1526","mi":"E","v":541,"sc":3,"cc":3,"lpe":81.7,"lpr":55369.18,"lq":1.84,"spr":74597.26,"sq":2.19,"sb":0.04},{"ci":"15915","ri":"15934","ti":"16000","tc":"Ямусукро","wi":3.36,"pi":"1526","mi":"E","v":104,"sc":3,"cc":3,"lpe":81.73,"lpr":41381.1,"lq":1.53,"spr":45647.97,"sq":1.98,"sb":0.02},{"ci":"422187","ri":"422188","ti":"422942","tc":"Баямо","wi":13.94,"pi":"1526","mi":"E","v":623,"sc":1,"cc":1,"lpe":89.25,"lpr":24502.67,"lq":1.05,"spr":25631.6,"sq":1.6,"sb":0.0},{"ci":"422187","ri":"422188","ti":"422189","tc":"Гавана","wi":32.08,"pi":"1526","mi":"E","v":15185,"sc":13,"cc":11,"lpe":80.78,"lpr":49432.44,"lq":7.11,"spr":60547.37,"sq":7.64,"sb":0.69},{"ci":"422187","ri":"422188","ti":"422193","tc":"Гуантанамо","wi":19.3,"pi":"1526","mi":"D","v":301,"sc":4,"cc":4,"lpe":40.53,"lpr":185113.32,"lq":4.93,"spr":134083.8,"sq":5.53,"sb":0.62},{"ci":"422187","ri":"422188","ti":"422191","tc":"Камагуэй","wi":8.34,"pi":"1526","mi":"E","v":1581,"sc":4,"cc":4,"lpe":78.75,"lpr":45534.46,"lq":1.64,"spr":68373.92,"sq":3.17,"sb":0.25},{"ci":"422187","ri":"422188","ti":"422979","tc":"Лас Тунас","wi":15.1,"pi":"1526","mi":"E","v":650,"sc":1,"cc":1,"lpe":97.69,"lpr":56897.68,"lq":1.0,"spr":56830.81,"sq":1.07,"sb":0.0},{"ci":"422187","ri":"422188","ti":"422192","tc":"Ольгин","wi":10.0,"pi":"1526","mi":"E","v":245,"sc":2,"cc":2,"lpe":70.61,"lpr":106842.28,"lq":6.41,"spr":144405.4,"sq":6.66,"sb":0.53},{"ci":"422187","ri":"422188","ti":"422195","tc":"Пинар-дель-Рио","wi":11.53,"pi":"1526","mi":"D","v":98,"sc":3,"cc":2,"lpe":32.65,"lpr":127538.88,"lq":3.58,"spr":129371.95,"sq":4.44,"sb":0.72},{"ci":"422187","ri":"422188","ti":"422194","tc":"Санта-Клара","wi":12.46,"pi":"1526","mi":"E","v":129,"sc":3,"cc":2,"lpe":65.12,"lpr":61149.1,"lq":7.05,"spr":91346.2,"sq":7.32,"sb":0.88},{"ci":"422187","ri":"422188","ti":"422190","tc":"Сантьяго-де-Куба","wi":18.69,"pi":"1526","mi":"E","v":5591,"sc":4,"cc":4,"lpe":88.54,"lpr":28054.02,"lq":4.83,"spr":36216.88,"sq":5.37,"sb":0.45},{"ci":"15911","ri":"15930","ti":"15987","tc":"Джахра","wi":27.67,"pi":"1526","mi":"E","v":1585,"sc":3,"cc":3,"lpe":82.78,"lpr":40153.87,"lq":6.69,"spr":72156.81,"sq":7.48,"sb":0.85},{"ci":"15911","ri":"15930","ti":"15986","tc":"Эль-Кувейт","wi":30.81,"pi":"1526","mi":"E","v":11699,"sc":4,"cc":4,"lpe":76.42,"lpr":58612.98,"lq":7.3,"spr":87479.5,"sq":8.0,"sb":0.98},{"ci":"325645","ri":"325646","ti":"325648","tc":"Даугавпилс","wi":10.86,"pi":"1526","mi":"D","v":145,"sc":2,"cc":2,"lpe":23.45,"lpr":130907.97,"lq":4.48,"spr":86468.8,"sq":4.92,"sb":1.99},{"ci":"325645","ri":"325646","ti":"325649","tc":"Лиепая","wi":11.13,"pi":"1526","mi":"E","v":838,"sc":1,"cc":1,"lpe":89.02,"lpr":19056.6,"lq":3.07,"spr":20806.95,"sq":3.17,"sb":0.32},{"ci":"325645","ri":"325646","ti":"325647","tc":"Рига","wi":17.24,"pi":"1526","mi":"E","v":1229,"sc":7,"cc":7,"lpe":58.67,"lpr":84576.93,"lq":7.92,"spr":149961.34,"sq":9.32,"sb":1.75},{"ci":"325650","ri":"325651","ti":"325652","tc":"Вильнюс","wi":18.74,"pi":"1526","mi":"E","v":1833,"sc":5,"cc":5,"lpe":65.52,"lpr":61597.53,"lq":7.59,"spr":71709.6,"sq":8.73,"sb":1.61},{"ci":"325650","ri":"325651","ti":"325653","tc":"Каунас","wi":13.06,"pi":"1526","mi":"D","v":320,"sc":5,"cc":5,"lpe":35.31,"lpr":170637.76,"lq":5.88,"spr":172794.07,"sq":6.41,"sb":1.69},{"ci":"325650","ri":"325651","ti":"325654","tc":"Клайпеда","wi":12.1,"pi":"1526","mi":"D","v":196,"sc":2,"cc":2,"lpe":47.45,"lpr":30920.25,"lq":4.68,"spr":48906.04,"sq":5.89,"sb":2.88},{"ci":"423081","ri":"423082","ti":"423083","tc":"Вадуц","wi":157.87,"pi":"1526","mi":"AAA","v":22,"sc":3,"cc":3,"lpe":0.0,"lpr":189325.96,"lq":4.67,"spr":553711.95,"sq":7.91,"sb":4.68},{"ci":"15914","ri":"15933","ti":"15998","tc":"Бамако","wi":3.99,"pi":"1526","mi":"E","v":11459,"sc":2,"cc":2,"lpe":93.67,"lpr":10741.41,"lq":1.0,"spr":13707.3,"sq":1.61,"sb":0.29},{"ci":"15914","ri":"15933","ti":"15999","tc":"Гао","wi":9.48,"pi":"1526","mi":"E","v":1110,"sc":3,"cc":3,"lpe":83.51,"lpr":26642.21,"lq":2.54,"spr":45129.12,"sq":3.86,"sb":0.73},{"ci":"15914","ri":"15933","ti":"422959","tc":"Сикасо","wi":4.65,"pi":"1526","mi":"E","v":741,"sc":2,"cc":2,"lpe":95.82,"lpr":11540.66,"lq":1.0,"spr":13466.76,"sq":1.29,"sb":0.13},{"ci":"422607","ri":"422608","ti":"422633","tc":"Гуадалупе","wi":11.74,"pi":"1526","mi":"E","v":697,"sc":2,"cc":2,"lpe":72.17,"lpr":75711.84,"lq":5.73,"spr":121292.76,"sq":6.38,"sb":0.79},{"ci":"422607","ri":"422608","ti":"422629","tc":"Кульякан","wi":4.9,"pi":"1526","mi":"E","v":373,"sc":1,"cc":1,"lpe":90.35,"lpr":56418.65,"lq":1.0,"spr":57343.39,"sq":1.39,"sb":0.0},{"ci":"422607","ri":"422608","ti":"422630","tc":"Мехикали","wi":4.16,"pi":"1526","mi":"E","v":733,"sc":2,"cc":2,"lpe":86.77,"lpr":7381.24,"lq":1.21,"spr":14373.92,"sq":2.67,"sb":0.07},{"ci":"422607","ri":"422608","ti":"422620","tc":"Монтеррей","wi":16.65,"pi":"1526","mi":"E","v":3435,"sc":5,"cc":5,"lpe":77.06,"lpr":14498.52,"lq":2.42,"spr":30694.76,"sq":4.28,"sb":0.85},{"ci":"422607","ri":"422608","ti":"422627","tc":"Сальтильо","wi":11.1,"pi":"1526","mi":"D","v":540,"sc":3,"cc":3,"lpe":37.04,"lpr":106456.98,"lq":5.73,"spr":142761.84,"sq":5.9,"sb":0.86},{"ci":"422607","ri":"422608","ti":"422616","tc":"Сьюдад-Хуарес","wi":16.25,"pi":"1526","mi":"E","v":4338,"sc":4,"cc":4,"lpe":82.96,"lpr":15183.51,"lq":2.58,"spr":28052.19,"sq":4.13,"sb":0.72},{"ci":"422607","ri":"422608","ti":"422617","tc":"Тихуана","wi":22.95,"pi":"1526","mi":"E","v":4871,"sc":4,"cc":4,"lpe":68.45,"lpr":41155.99,"lq":7.38,"spr":77106.14,"sq":8.66,"sb":1.33},{"ci":"422607","ri":"422608","ti":"422622","tc":"Чиуауа","wi":5.16,"pi":"1526","mi":"E","v":415,"sc":2,"cc":2,"lpe":85.78,"lpr":39535.01,"lq":4.66,"spr":46378.74,"sq":4.93,"sb":0.0},{"ci":"422607","ri":"422608","ti":"422625","tc":"Эрмосильо","wi":10.44,"pi":"1526","mi":"E","v":1660,"sc":2,"cc":2,"lpe":83.43,"lpr":34629.65,"lq":5.35,"spr":52687.99,"sq":5.86,"sb":0.51},{"ci":"422607","ri":"422609","ti":"422626","tc":"Агуаскальентес","wi":9.84,"pi":"1526","mi":"E","v":1176,"sc":1,"cc":1,"lpe":85.97,"lpr":48598.24,"lq":4.84,"spr":67034.71,"sq":5.1,"sb":0.29},{"ci":"422607","ri":"422609","ti":"422632","tc":"Акапулько","wi":24.18,"pi":"1526","mi":"D","v":2152,"sc":4,"cc":4,"lpe":36.01,"lpr":69108.37,"lq":6.02,"spr":91688.66,"sq":5.61,"sb":0.5},{"ci":"422607","ri":"422609","ti":"422614","tc":"Гвадалахара","wi":21.23,"pi":"1526","mi":"E","v":5041,"sc":9,"cc":9,"lpe":70.88,"lpr":23992.43,"lq":4.3,"spr":49806.1,"sq":6.11,"sb":1.02},{"ci":"422607","ri":"422609","ti":"422618","tc":"Леон","wi":15.31,"pi":"1526","mi":"E","v":4437,"sc":3,"cc":3,"lpe":83.43,"lpr":14239.29,"lq":2.69,"spr":26509.31,"sq":4.13,"sb":0.7},{"ci":"422607","ri":"422609","ti":"422628","tc":"Сан-Луис-Потоси","wi":17.02,"pi":"1526","mi":"D","v":2370,"sc":2,"cc":2,"lpe":35.61,"lpr":42515.2,"lq":5.28,"spr":53901.62,"sq":6.67,"sb":1.53},{"ci":"422607","ri":"422609","ti":"422619","tc":"Сапопан","wi":11.6,"pi":"1526","mi":"E","v":2601,"sc":3,"cc":2,"lpe":80.24,"lpr":9015.37,"lq":1.65,"spr":18473.57,"sq":3.59,"sb":0.76},{"ci":"422607","ri":"422610","ti":"422612","tc":"Мехико","wi":31.35,"pi":"1526","mi":"E","v":59501,"sc":9,"cc":9,"lpe":76.11,"lpr":66856.88,"lq":7.44,"spr":81020.8,"sq":7.73,"sb":0.66},{"ci":"422607","ri":"422610","ti":"422623","tc":"Наукальпан","wi":28.37,"pi":"1526","mi":"E","v":2598,"sc":4,"cc":4,"lpe":76.21,"lpr":54755.24,"lq":6.95,"spr":74059.04,"sq":7.61,"sb":0.81},{"ci":"422607","ri":"422610","ti":"422621","tc":"Несауалькойотль","wi":26.48,"pi":"1526","mi":"E","v":3628,"sc":4,"cc":4,"lpe":77.07,"lpr":38720.82,"lq":6.57,"spr":70486.55,"sq":7.68,"sb":0.92},{"ci":"422607","ri":"422610","ti":"422615","tc":"Пуэбла-де-Сарагоса","wi":27.35,"pi":"1526","mi":"E","v":5341,"sc":6,"cc":5,"lpe":72.08,"lpr":34445.98,"lq":6.2,"spr":66698.98,"sq":7.49,"sb":1.08},{"ci":"422607","ri":"422610","ti":"422613","tc":"Экатепек-де-Морелос","wi":29.72,"pi":"1526","mi":"E","v":6154,"sc":8,"cc":8,"lpe":68.12,"lpr":23102.02,"lq":4.03,"spr":50687.45,"sq":6.04,"sb":1.15},{"ci":"422607","ri":"422611","ti":"422631","tc":"Канкун","wi":11.19,"pi":"1526","mi":"E","v":1952,"sc":2,"cc":2,"lpe":88.01,"lpr":17141.67,"lq":2.86,"spr":28853.47,"sq":3.94,"sb":0.62},{"ci":"422607","ri":"422611","ti":"422624","tc":"Мерида","wi":9.7,"pi":"1526","mi":"E","v":3377,"sc":1,"cc":1,"lpe":89.93,"lpr":19279.49,"lq":2.82,"spr":29420.14,"sq":3.54,"sb":0.54},{"ci":"15913","ri":"15932","ti":"15991","tc":"Абуджа","wi":6.92,"pi":"1526","mi":"E","v":3072,"sc":3,"cc":3,"lpe":75.46,"lpr":25899.9,"lq":5.75,"spr":54733.73,"sq":7.22,"sb":0.43},{"ci":"15913","ri":"15932","ti":"15997","tc":"Бенин-сити","wi":3.71,"pi":"1526","mi":"D","v":296,"sc":1,"cc":1,"lpe":15.54,"lpr":56261.08,"lq":7.66,"spr":75043.95,"sq":10.4,"sb":1.1},{"ci":"15913","ri":"15932","ti":"423024","tc":"Джалинго","wi":2.46,"pi":"1526","mi":"","v":425,"sc":0,"cc":0,"lpe":100.0,"lpr":10439.34,"lq":1.0,"spr":10439.34,"sq":1.0,"sb":0.0},{"ci":"15913","ri":"15932","ti":"15994","tc":"Ибадан","wi":3.64,"pi":"1526","mi":"E","v":1070,"sc":3,"cc":3,"lpe":89.63,"lpr":57964.27,"lq":7.3,"spr":75128.72,"sq":7.6,"sb":0.39},{"ci":"15913","ri":"15932","ti":"15995","tc":"Кадуна","wi":3.67,"pi":"1526","mi":"E","v":117,"sc":1,"cc":1,"lpe":70.09,"lpr":22352.38,"lq":7.17,"spr":56050.39,"sq":8.35,"sb":1.05},{"ci":"15913","ri":"15932","ti":"15993","tc":"Кано","wi":3.88,"pi":"1526","mi":"E","v":965,"sc":1,"cc":1,"lpe":61.66,"lpr":20702.4,"lq":6.0,"spr":44205.11,"sq":7.9,"sb":0.5},{"ci":"15913","ri":"15932","ti":"15992","tc":"Лагос","wi":4.32,"pi":"1526","mi":"E","v":2156,"sc":2,"cc":2,"lpe":78.06,"lpr":10943.29,"lq":2.54,"spr":29785.51,"sq":4.6,"sb":0.71},{"ci":"15913","ri":"15932","ti":"423023","tc":"Лафия","wi":2.51,"pi":"1526","mi":"","v":1097,"sc":0,"cc":0,"lpe":100.0,"lpr":10983.91,"lq":1.0,"spr":10983.91,"sq":1.0,"sb":0.0},{"ci":"15913","ri":"15932","ti":"15996","tc":"Порт-Харкорт","wi":4.42,"pi":"1526","mi":"E","v":3622,"sc":4,"cc":4,"lpe":92.44,"lpr":15845.73,"lq":1.0,"spr":16896.13,"sq":1.26,"sb":0.0},{"ci":"15913","ri":"15932","ti":"423000","tc":"Энугу","wi":2.45,"pi":"1526","mi":"","v":3040,"sc":0,"cc":0,"lpe":100.0,"lpr":10077.31,"lq":1.0,"spr":10077.31,"sq":1.0,"sb":0.0},{"ci":"359837","ri":"359838","ti":"359845","tc":"Алмере","wi":15.2,"pi":"1526","mi":"E","v":275,"sc":1,"cc":1,"lpe":90.55,"lpr":107414.91,"lq":1.0,"spr":118668.32,"sq":1.62,"sb":0.19},{"ci":"359837","ri":"359838","ti":"359839","tc":"Амстердам","wi":27.34,"pi":"1526","mi":"E","v":5122,"sc":5,"cc":5,"lpe":74.15,"lpr":12241.07,"lq":2.42,"spr":29822.55,"sq":4.47,"sb":1.14},{"ci":"359837","ri":"359838","ti":"359840","tc":"Гаага","wi":28.21,"pi":"1526","mi":"E","v":3325,"sc":4,"cc":4,"lpe":79.16,"lpr":52648.92,"lq":8.17,"spr":79244.3,"sq":8.84,"sb":1.03},{"ci":"359837","ri":"359838","ti":"359846","tc":"Гронинген","wi":21.08,"pi":"1526","mi":"E","v":821,"sc":2,"cc":2,"lpe":70.4,"lpr":54216.1,"lq":7.41,"spr":87323.32,"sq":7.69,"sb":1.17},{"ci":"359837","ri":"359838","ti":"359844","tc":"Маастрихт","wi":16.74,"pi":"1526","mi":"E","v":132,"sc":3,"cc":3,"lpe":64.39,"lpr":52008.82,"lq":4.79,"spr":96506.13,"sq":5.22,"sb":1.35},{"ci":"359837","ri":"359838","ti":"359841","tc":"Роттердам","wi":32.77,"pi":"1526","mi":"E","v":5202,"sc":3,"cc":3,"lpe":85.52,"lpr":50683.43,"lq":7.69,"spr":66032.1,"sq":8.17,"sb":0.71},{"ci":"359837","ri":"359838","ti":"359842","tc":"Утрехт","wi":26.26,"pi":"1526","mi":"E","v":1896,"sc":3,"cc":3,"lpe":79.22,"lpr":58830.11,"lq":7.86,"spr":96450.25,"sq":8.55,"sb":1.02},{"ci":"359837","ri":"359838","ti":"359843","tc":"Эйндховен","wi":20.87,"pi":"1526","mi":"E","v":542,"sc":1,"cc":1,"lpe":95.2,"lpr":86447.87,"lq":1.0,"spr":109164.39,"sq":1.49,"sb":0.19},{"ci":"335165","ri":"335166","ti":"335168","tc":"Берген","wi":14.57,"pi":"1526","mi":"","v":272,"sc":0,"cc":0,"lpe":100.0,"lpr":87416.72,"lq":4.46,"spr":87416.72,"sq":4.46,"sb":0.0},{"ci":"335165","ri":"335166","ti":"335171","tc":"Берум","wi":15.58,"pi":"1526","mi":"E","v":229,"sc":1,"cc":1,"lpe":98.69,"lpr":92722.02,"lq":5.62,"spr":92912.8,"sq":5.62,"sb":0.0},{"ci":"335165","ri":"335166","ti":"335167","tc":"Осло","wi":20.02,"pi":"1526","mi":"E","v":5635,"sc":4,"cc":4,"lpe":84.84,"lpr":15161.72,"lq":2.68,"spr":28331.26,"sq":3.94,"sb":0.72},{"ci":"335165","ri":"335166","ti":"335169","tc":"Ставангер","wi":20.7,"pi":"1526","mi":"E","v":340,"sc":2,"cc":2,"lpe":97.35,"lpr":98256.11,"lq":1.23,"spr":98390.51,"sq":1.42,"sb":0.0},{"ci":"335165","ri":"335166","ti":"335170","tc":"Тронхейм","wi":15.16,"pi":"1526","mi":"E","v":675,"sc":1,"cc":1,"lpe":65.33,"lpr":46517.58,"lq":4.25,"spr":58124.82,"sq":4.31,"sb":0.0},{"ci":"15910","ri":"15929","ti":"15984","tc":"Абу-Даби","wi":31.98,"pi":"1526","mi":"E","v":8176,"sc":5,"cc":5,"lpe":77.51,"lpr":50707.7,"lq":7.52,"spr":79010.74,"sq":8.18,"sb":0.86},{"ci":"15910","ri":"15929","ti":"15985","tc":"Дубай","wi":31.46,"pi":"1526","mi":"E","v":17104,"sc":4,"cc":4,"lpe":73.47,"lpr":14351.39,"lq":2.67,"spr":31723.47,"sq":4.76,"sb":1.11},{"ci":"15909","ri":"15928","ti":"15983","tc":"Даммам","wi":21.67,"pi":"1526","mi":"E","v":5076,"sc":3,"cc":3,"lpe":80.63,"lpr":32612.51,"lq":5.72,"spr":60347.56,"sq":6.77,"sb":0.85},{"ci":"15909","ri":"15928","ti":"15980","tc":"Джидда","wi":20.46,"pi":"1526","mi":"E","v":27426,"sc":5,"cc":5,"lpe":73.98,"lpr":10620.26,"lq":2.1,"spr":21564.68,"sq":4.04,"sb":1.09},{"ci":"15909","ri":"15928","ti":"15982","tc":"Медина","wi":23.13,"pi":"1526","mi":"E","v":7272,"sc":2,"cc":2,"lpe":84.01,"lpr":33684.85,"lq":5.66,"spr":54759.42,"sq":6.54,"sb":0.7},{"ci":"15909","ri":"15928","ti":"15981","tc":"Мекка","wi":20.93,"pi":"1526","mi":"E","v":7148,"sc":3,"cc":3,"lpe":82.37,"lpr":43545.34,"lq":7.49,"spr":63973.62,"sq":8.15,"sb":0.77},{"ci":"15909","ri":"15928","ti":"15979","tc":"Эр-Рияд","wi":26.02,"pi":"1526","mi":"E","v":41211,"sc":4,"cc":4,"lpe":77.46,"lpr":27704.99,"lq":4.57,"spr":47790.61,"sq":6.13,"sb":0.92},{"ci":"422653","ri":"422659","ti":"422661","tc":"Лос-Анджелес","wi":31.96,"pi":"1526","mi":"E","v":14611,"sc":11,"cc":10,"lpe":72.44,"lpr":29864.74,"lq":5.28,"spr":55445.63,"sq":6.86,"sb":0.86},{"ci":"422653","ri":"422659","ti":"422667","tc":"Сан-Диего","wi":24.19,"pi":"1526","mi":"E","v":5075,"sc":6,"cc":5,"lpe":63.29,"lpr":48175.32,"lq":7.08,"spr":78628.27,"sq":8.13,"sb":0.74},{"ci":"422653","ri":"422659","ti":"422669","tc":"Сан-Хосе","wi":24.95,"pi":"1526","mi":"E","v":3864,"sc":4,"cc":4,"lpe":75.62,"lpr":25107.48,"lq":4.23,"spr":45196.44,"sq":5.5,"sb":0.71},{"ci":"422653","ri":"422654","ti":"422683","tc":"Бостон","wi":34.38,"pi":"1526","mi":"E","v":2441,"sc":7,"cc":7,"lpe":68.29,"lpr":36365.94,"lq":6.17,"spr":71469.58,"sq":7.08,"sb":1.34},{"ci":"422653","ri":"422654","ti":"422685","tc":"Хартфорд","wi":16.45,"pi":"1526","mi":"E","v":412,"sc":2,"cc":2,"lpe":79.85,"lpr":14587.16,"lq":2.54,"spr":30712.8,"sq":4.08,"sb":0.97},{"ci":"422653","ri":"422655","ti":"422682","tc":"Вашингтон","wi":24.05,"pi":"1526","mi":"E","v":2458,"sc":6,"cc":6,"lpe":72.46,"lpr":27780.02,"lq":5.02,"spr":51442.72,"sq":5.95,"sb":0.82},{"ci":"422653","ri":"422655","ti":"422660","tc":"Нью-Йорк","wi":38.58,"pi":"1526","mi":"D","v":32708,"sc":17,"cc":16,"lpe":37.35,"lpr":64944.87,"lq":7.22,"spr":102601.52,"sq":8.19,"sb":1.53},{"ci":"422653","ri":"422655","ti":"422664","tc":"Филадельфия","wi":31.62,"pi":"1526","mi":"E","v":5735,"sc":8,"cc":7,"lpe":68.09,"lpr":54541.9,"lq":7.83,"spr":86685.15,"sq":8.61,"sb":0.91},{"ci":"422653","ri":"422657","ti":"422671","tc":"Индианаполис","wi":25.98,"pi":"1526","mi":"E","v":3133,"sc":6,"cc":6,"lpe":76.83,"lpr":20036.51,"lq":3.44,"spr":38188.09,"sq":4.88,"sb":0.8},{"ci":"422653","ri":"422657","ti":"422674","tc":"Колумбус","wi":26.42,"pi":"1526","mi":"E","v":3118,"sc":4,"cc":4,"lpe":68.38,"lpr":70873.11,"lq":6.03,"spr":78421.74,"sq":6.81,"sb":0.63},{"ci":"422653","ri":"422657","ti":"422662","tc":"Чикаго","wi":33.55,"pi":"1526","mi":"E","v":10219,"sc":6,"cc":6,"lpe":74.01,"lpr":32707.23,"lq":5.6,"spr":58465.49,"sq":6.81,"sb":0.86},{"ci":"422653","ri":"422658","ti":"422666","tc":"Сан-Антонио","wi":34.19,"pi":"1526","mi":"E","v":5320,"sc":5,"cc":4,"lpe":69.62,"lpr":36533.14,"lq":6.02,"spr":65021.65,"sq":7.17,"sb":0.67},{"ci":"422653","ri":"422658","ti":"422665","tc":"Финикс","wi":33.44,"pi":"1526","mi":"E","v":5568,"sc":6,"cc":6,"lpe":73.42,"lpr":45041.31,"lq":7.47,"spr":79492.43,"sq":8.26,"sb":1.19},{"ci":"422653","ri":"422658","ti":"422663","tc":"Хьюстон","wi":35.75,"pi":"1526","mi":"E","v":8214,"sc":5,"cc":4,"lpe":73.01,"lpr":60698.18,"lq":7.19,"spr":93252.5,"sq":7.99,"sb":0.53},{"ci":"422653","ri":"422656","ti":"422672","tc":"Джексонвиль","wi":20.72,"pi":"1526","mi":"E","v":4308,"sc":5,"cc":5,"lpe":85.21,"lpr":38026.79,"lq":6.29,"spr":54846.29,"sq":6.91,"sb":0.58},{"ci":"422653","ri":"422656","ti":"422679","tc":"Мемфис","wi":20.67,"pi":"1526","mi":"E","v":2330,"sc":6,"cc":6,"lpe":76.44,"lpr":43709.22,"lq":6.12,"spr":63312.11,"sq":7.13,"sb":0.83},{"ci":"422653","ri":"422656","ti":"422675","tc":"Шарлотт","wi":26.28,"pi":"1526","mi":"E","v":2915,"sc":7,"cc":7,"lpe":68.34,"lpr":34228.56,"lq":5.76,"spr":55602.33,"sq":6.66,"sb":0.89},{"ci":"15908","ri":"15927","ti":"15975","tc":"Адана","wi":8.62,"pi":"1526","mi":"E","v":2582,"sc":3,"cc":3,"lpe":88.73,"lpr":21179.24,"lq":3.54,"spr":29931.54,"sq":4.16,"sb":0.39},{"ci":"15908","ri":"15927","ti":"15974","tc":"Анкара","wi":17.15,"pi":"1526","mi":"E","v":27873,"sc":8,"cc":8,"lpe":78.1,"lpr":14490.79,"lq":2.65,"spr":27036.37,"sq":4.25,"sb":0.82},{"ci":"15908","ri":"15927","ti":"15978","tc":"Анталья","wi":17.39,"pi":"1526","mi":"E","v":7911,"sc":3,"cc":3,"lpe":82.87,"lpr":30614.06,"lq":5.32,"spr":49058.27,"sq":6.31,"sb":0.38},{"ci":"15908","ri":"15927","ti":"15976","tc":"Газиантеп","wi":7.44,"pi":"1526","mi":"D","v":1275,"sc":3,"cc":3,"lpe":47.06,"lpr":71120.0,"lq":2.96,"spr":65036.56,"sq":4.2,"sb":1.11},{"ci":"15908","ri":"15927","ti":"15973","tc":"Измир","wi":13.41,"pi":"1526","mi":"E","v":15158,"sc":5,"cc":5,"lpe":81.09,"lpr":19877.85,"lq":3.17,"spr":35996.24,"sq":4.35,"sb":0.65},{"ci":"15908","ri":"15927","ti":"15977","tc":"Конья","wi":7.8,"pi":"1526","mi":"E","v":1465,"sc":2,"cc":2,"lpe":67.85,"lpr":45515.59,"lq":7.37,"spr":78464.5,"sq":8.17,"sb":1.28},{"ci":"15908","ri":"15926","ti":"15972","tc":"Бурса","wi":12.22,"pi":"1526","mi":"E","v":6497,"sc":7,"cc":6,"lpe":83.92,"lpr":14436.67,"lq":2.88,"spr":24882.97,"sq":3.76,"sb":0.37},{"ci":"15908","ri":"15926","ti":"15971","tc":"Стамбул","wi":16.11,"pi":"1526","mi":"E","v":82423,"sc":11,"cc":10,"lpe":79.29,"lpr":20393.39,"lq":3.47,"spr":34492.52,"sq":4.91,"sb":0.72},{"ci":"310392","ri":"310393","ti":"310397","tc":"Андижан","wi":2.78,"pi":"1526","mi":"E","v":1334,"sc":1,"cc":1,"lpe":99.85,"lpr":22527.39,"lq":1.0,"spr":22583.57,"sq":1.0,"sb":0.0},{"ci":"310392","ri":"310393","ti":"310399","tc":"Бухара","wi":4.3,"pi":"1526","mi":"E","v":717,"sc":2,"cc":2,"lpe":84.66,"lpr":13754.09,"lq":2.43,"spr":23749.98,"sq":3.55,"sb":0.67},{"ci":"310392","ri":"310393","ti":"310395","tc":"Наманган","wi":7.21,"pi":"1526","mi":"E","v":486,"sc":2,"cc":2,"lpe":88.27,"lpr":39145.94,"lq":2.2,"spr":48593.84,"sq":3.15,"sb":0.44},{"ci":"310392","ri":"310393","ti":"310400","tc":"Нукус","wi":2.93,"pi":"1526","mi":"","v":98,"sc":0,"cc":0,"lpe":100.0,"lpr":103500.71,"lq":1.0,"spr":103500.71,"sq":1.0,"sb":0.0},{"ci":"310392","ri":"310393","ti":"310396","tc":"Самарканд","wi":16.29,"pi":"1526","mi":"AAA","v":463,"sc":4,"cc":4,"lpe":0.0,"lpr":207062.03,"lq":2.97,"spr":83941.68,"sq":3.29,"sb":4.37},{"ci":"310392","ri":"310393","ti":"310394","tc":"Ташкент","wi":15.97,"pi":"1526","mi":"E","v":16008,"sc":4,"cc":4,"lpe":79.87,"lpr":18096.0,"lq":3.09,"spr":31594.84,"sq":4.48,"sb":0.38},{"ci":"310392","ri":"310393","ti":"310398","tc":"Фергана","wi":12.45,"pi":"1526","mi":"E","v":337,"sc":5,"cc":5,"lpe":71.81,"lpr":108404.24,"lq":8.12,"spr":124767.14,"sq":8.84,"sb":0.96},{"ci":"301309","ri":"301310","ti":"301315","tc":"Рованиеми","wi":12.57,"pi":"1526","mi":"D","v":96,"sc":3,"cc":3,"lpe":50.0,"lpr":111751.07,"lq":5.85,"spr":132528.17,"sq":6.56,"sb":0.93},{"ci":"301309","ri":"301310","ti":"301313","tc":"Тампере","wi":24.73,"pi":"1526","mi":"E","v":556,"sc":3,"cc":3,"lpe":78.78,"lpr":152705.71,"lq":2.62,"spr":160375.98,"sq":3.14,"sb":0.13},{"ci":"301309","ri":"301310","ti":"301314","tc":"Турку","wi":22.72,"pi":"1526","mi":"E","v":561,"sc":3,"cc":3,"lpe":90.02,"lpr":55701.26,"lq":1.08,"spr":64412.03,"sq":1.61,"sb":0.13},{"ci":"301309","ri":"301310","ti":"301311","tc":"Хельсинки","wi":30.62,"pi":"1526","mi":"E","v":2334,"sc":10,"cc":10,"lpe":60.63,"lpr":114587.93,"lq":7.86,"spr":149590.8,"sq":9.03,"sb":1.61},{"ci":"301309","ri":"301310","ti":"301312","tc":"Эспоо","wi":23.71,"pi":"1526","mi":"E","v":1452,"sc":4,"cc":4,"lpe":95.94,"lpr":84943.48,"lq":1.0,"spr":86951.09,"sq":1.21,"sb":0.04},{"ci":"15906","ri":"15923","ti":"3039","tc":"Гавр","wi":18.12,"pi":"1526","mi":"E","v":827,"sc":2,"cc":2,"lpe":75.82,"lpr":68173.96,"lq":6.76,"spr":81191.14,"sq":7.05,"sb":0.54},{"ci":"15906","ri":"15923","ti":"15961","tc":"Дижон","wi":28.49,"pi":"1526","mi":"E","v":1404,"sc":3,"cc":3,"lpe":72.22,"lpr":29934.26,"lq":4.98,"spr":40613.87,"sq":5.62,"sb":0.14},{"ci":"15906","ri":"15923","ti":"3041","tc":"Нант","wi":13.84,"pi":"1526","mi":"E","v":691,"sc":1,"cc":1,"lpe":99.71,"lpr":185001.56,"lq":1.0,"spr":186220.08,"sq":1.03,"sb":0.01},{"ci":"15906","ri":"15923","ti":"3031","tc":"Париж","wi":21.01,"pi":"1526","mi":"E","v":17450,"sc":8,"cc":7,"lpe":81.08,"lpr":13419.62,"lq":2.49,"spr":26029.94,"sq":3.92,"sb":0.82},{"ci":"15906","ri":"15923","ti":"3040","tc":"Реймс","wi":14.01,"pi":"1526","mi":"E","v":330,"sc":1,"cc":1,"lpe":72.42,"lpr":50825.48,"lq":7.82,"spr":100233.94,"sq":8.73,"sb":1.04},{"ci":"15906","ri":"15923","ti":"3038","tc":"Ренн","wi":14.04,"pi":"1526","mi":"E","v":673,"sc":2,"cc":2,"lpe":78.16,"lpr":32935.04,"lq":4.62,"spr":62118.62,"sq":5.51,"sb":0.82},{"ci":"15906","ri":"15923","ti":"3036","tc":"Страсбург","wi":18.17,"pi":"1526","mi":"E","v":1775,"sc":4,"cc":4,"lpe":75.61,"lpr":45213.29,"lq":7.47,"spr":82659.71,"sq":8.22,"sb":1.0},{"ci":"15906","ri":"15922","ti":"15960","tc":"Аяччо","wi":12.83,"pi":"1526","mi":"E","v":169,"sc":3,"cc":3,"lpe":69.23,"lpr":41001.08,"lq":5.04,"spr":60368.16,"sq":5.6,"sb":0.16},{"ci":"15906","ri":"15922","ti":"3037","tc":"Бордо","wi":17.8,"pi":"1526","mi":"D","v":1410,"sc":2,"cc":2,"lpe":11.42,"lpr":42494.47,"lq":4.57,"spr":53062.13,"sq":5.38,"sb":3.45},{"ci":"15906","ri":"15922","ti":"3033","tc":"Лион","wi":20.42,"pi":"1526","mi":"E","v":2766,"sc":4,"cc":4,"lpe":75.42,"lpr":34313.54,"lq":6.73,"spr":68871.02,"sq":7.86,"sb":1.13},{"ci":"15906","ri":"15922","ti":"3032","tc":"Марсель","wi":20.62,"pi":"1526","mi":"E","v":5107,"sc":5,"cc":5,"lpe":78.83,"lpr":18579.3,"lq":3.65,"spr":37088.76,"sq":5.11,"sb":0.9},{"ci":"15906","ri":"15922","ti":"15958","tc":"Монпелье","wi":14.2,"pi":"1526","mi":"E","v":1237,"sc":2,"cc":2,"lpe":62.33,"lpr":9451.73,"lq":2.15,"spr":20005.89,"sq":3.26,"sb":0.23},{"ci":"15906","ri":"15922","ti":"3035","tc":"Ницца","wi":17.17,"pi":"1526","mi":"E","v":4630,"sc":3,"cc":3,"lpe":81.4,"lpr":15054.53,"lq":2.47,"spr":28706.44,"sq":4.13,"sb":0.73},{"ci":"15906","ri":"15922","ti":"15959","tc":"Сент-Этьен","wi":14.6,"pi":"1526","mi":"D","v":269,"sc":3,"cc":2,"lpe":46.47,"lpr":88291.75,"lq":6.46,"spr":154533.75,"sq":6.14,"sb":0.09},{"ci":"15906","ri":"15922","ti":"3034","tc":"Тулуза","wi":21.75,"pi":"1526","mi":"E","v":2880,"sc":2,"cc":2,"lpe":80.38,"lpr":54261.29,"lq":8.12,"spr":85173.08,"sq":8.75,"sb":0.95},{"ci":"325655","ri":"325656","ti":"325659","tc":"Нарва","wi":9.25,"pi":"1526","mi":"E","v":158,"sc":3,"cc":3,"lpe":85.44,"lpr":44572.0,"lq":1.0,"spr":57542.69,"sq":1.69,"sb":0.26},{"ci":"325655","ri":"325656","ti":"325657","tc":"Таллин","wi":20.96,"pi":"1526","mi":"E","v":2547,"sc":4,"cc":4,"lpe":92.85,"lpr":79213.78,"lq":1.0,"spr":82507.65,"sq":1.41,"sb":0.19},{"ci":"325655","ri":"325656","ti":"325658","tc":"Тарту","wi":9.04,"pi":"1526","mi":"E","v":928,"sc":3,"cc":3,"lpe":95.8,"lpr":35216.01,"lq":1.0,"spr":35753.07,"sq":1.14,"sb":0.03},{"ci":"15907","ri":"15924","ti":"15964","tc":"Ист-Лондон","wi":3.65,"pi":"1526","mi":"E","v":495,"sc":1,"cc":1,"lpe":64.24,"lpr":15084.78,"lq":2.52,"spr":16842.34,"sq":3.22,"sb":0.0},{"ci":"15907","ri":"15924","ti":"15962","tc":"Кейптаун","wi":17.19,"pi":"1526","mi":"E","v":11993,"sc":5,"cc":5,"lpe":80.95,"lpr":31317.63,"lq":5.28,"spr":55070.73,"sq":6.37,"sb":0.8},{"ci":"15907","ri":"15924","ti":"15965","tc":"Кимберли","wi":10.13,"pi":"1526","mi":"E","v":255,"sc":1,"cc":1,"lpe":88.24,"lpr":58742.41,"lq":2.83,"spr":58890.36,"sq":2.86,"sb":0.0},{"ci":"15907","ri":"15924","ti":"15963","tc":"Порт-Элизабет","wi":4.8,"pi":"1526","mi":"E","v":381,"sc":1,"cc":1,"lpe":90.81,"lpr":77266.02,"lq":2.04,"spr":79354.44,"sq":2.39,"sb":0.0},{"ci":"15907","ri":"15925","ti":"15968","tc":"Блумфонтейн","wi":10.81,"pi":"1526","mi":"E","v":1295,"sc":3,"cc":3,"lpe":86.72,"lpr":29926.81,"lq":4.93,"spr":48302.52,"sq":5.64,"sb":0.5},{"ci":"15907","ri":"15925","ti":"15966","tc":"Дурбан","wi":8.73,"pi":"1526","mi":"E","v":3348,"sc":3,"cc":3,"lpe":75.03,"lpr":51228.94,"lq":8.19,"spr":99086.14,"sq":9.03,"sb":0.92},{"ci":"15907","ri":"15925","ti":"15969","tc":"Йоханнесбург","wi":14.04,"pi":"1526","mi":"E","v":13051,"sc":5,"cc":5,"lpe":74.13,"lpr":16031.9,"lq":2.88,"spr":37852.33,"sq":4.7,"sb":0.94},{"ci":"15907","ri":"15925","ti":"15967","tc":"Питермарицбург","wi":7.42,"pi":"1526","mi":"E","v":3770,"sc":1,"cc":1,"lpe":97.48,"lpr":17849.37,"lq":1.0,"spr":18911.52,"sq":1.27,"sb":0.09},{"ci":"15907","ri":"15925","ti":"15970","tc":"Претория","wi":13.77,"pi":"1526","mi":"E","v":12618,"sc":5,"cc":5,"lpe":75.69,"lpr":26544.01,"lq":4.44,"spr":50633.48,"sq":5.94,"sb":0.62}]