[{"cn":"Meskhi Inc.","pi":"423722","ui":"6630069","t":129741,"r":8403,"q":26.5,"p":3100.0,"mot":"U","mo":0.0},{"cn":"kra5ava","pi":"423722","ui":"6566565","t":219847,"r":197086,"q":15.16,"p":4700.0,"mot":"U","mo":0.0},{"cn":"Redicson Трейд","pi":"423722","ui":"6636576","t":1610873,"r":871215,"q":20.03,"p":4200.0,"mot":"U","mo":0.0},{"cn":"Slon_97 Инвест","pi":"423722","ui":"6762533","t":20548,"r":12856,"q":25.23,"p":4000.0,"mot":"U","mo":0.0},{"cn":"BEREZOVES Трейд","pi":"423722","ui":"5706009","t":850035,"r":683856,"q":21.71,"p":5500.0,"mot":"U","mo":0.0},{"cn":"ООО \"Максимус\"","pi":"423722","ui":"6414857","t":16860488,"r":16840773,"q":41.86,"p":8109.0,"mot":"L","mo":100000.0},{"cn":"Гапонов и компания","pi":"423722","ui":"6541700","t":123549,"r":4535,"q":24.42,"p":2600.0,"mot":"L","mo":2500.0},{"cn":"LEGIS™","pi":"423722","ui":"6591779","t":2106,"r":2104,"q":17.19,"p":865.0,"mot":"L","mo":1.0}]