[{"ci":"3054","ri":"3055","ti":"3056","tc":"Баку","wi":8.62,"pi":"1482","mi":"D","v":154085,"sc":8,"cc":8,"lpe":25.83,"lpr":47.86,"lq":26.62,"spr":99.63,"sq":81.82,"sb":4.62},{"ci":"3054","ri":"3055","ti":"3057","tc":"Гянджа","wi":3.95,"pi":"1482","mi":"E","v":107449,"sc":5,"cc":4,"lpe":87.52,"lpr":38.61,"lq":6.29,"spr":37.97,"sq":7.33,"sb":0.08},{"ci":"3054","ri":"3055","ti":"422527","tc":"Ленкорань","wi":9.54,"pi":"1482","mi":"D","v":4686,"sc":3,"cc":3,"lpe":41.81,"lpr":211.24,"lq":6.77,"spr":318.49,"sq":11.82,"sb":0.0},{"ci":"3054","ri":"3055","ti":"3058","tc":"Сумгаит","wi":3.8,"pi":"1482","mi":"E","v":34354,"sc":4,"cc":4,"lpe":53.02,"lpr":38.15,"lq":13.81,"spr":34.43,"sq":17.81,"sb":0.41},{"ci":"303829","ri":"303830","ti":"303833","tc":"Ванадзор","wi":11.15,"pi":"1482","mi":"E","v":26437,"sc":3,"cc":3,"lpe":92.77,"lpr":160.56,"lq":1.92,"spr":170.65,"sq":5.88,"sb":0.12},{"ci":"303829","ri":"303830","ti":"303832","tc":"Гюмри","wi":10.01,"pi":"1482","mi":"E","v":132400,"sc":4,"cc":4,"lpe":89.68,"lpr":92.83,"lq":31.02,"spr":103.7,"sq":34.61,"sb":0.12},{"ci":"303829","ri":"303830","ti":"303831","tc":"Ереван","wi":28.17,"pi":"1482","mi":"E","v":189191,"sc":11,"cc":6,"lpe":17.34,"lpr":147.96,"lq":45.95,"spr":126.35,"sq":62.17,"sb":0.97},{"ci":"303253","ri":"303254","ti":"303257","tc":"Бургас","wi":13.97,"pi":"1482","mi":"E","v":36623,"sc":1,"cc":1,"lpe":83.24,"lpr":225.37,"lq":74.29,"spr":321.69,"sq":82.72,"sb":0.8},{"ci":"303253","ri":"303254","ti":"303256","tc":"Варна","wi":23.51,"pi":"1482","mi":"D","v":18367,"sc":1,"cc":1,"lpe":0.0,"lpr":215.74,"lq":83.34,"spr":785.69,"sq":127.89,"sb":4.68},{"ci":"303253","ri":"303254","ti":"422076","tc":"Казанлык","wi":10.74,"pi":"1482","mi":"E","v":19017,"sc":1,"cc":1,"lpe":99.74,"lpr":117.75,"lq":31.07,"spr":118.09,"sq":31.16,"sb":0.0},{"ci":"303253","ri":"303254","ti":"303261","tc":"Плевен","wi":12.98,"pi":"1482","mi":"","v":14831,"sc":0,"cc":0,"lpe":100.0,"lpr":797.98,"lq":1.0,"spr":797.98,"sq":1.0,"sb":0.0},{"ci":"303253","ri":"303254","ti":"303258","tc":"Пловдив","wi":17.4,"pi":"1482","mi":"E","v":29590,"sc":1,"cc":1,"lpe":86.88,"lpr":199.22,"lq":43.26,"spr":278.06,"sq":54.51,"sb":0.63},{"ci":"303253","ri":"303254","ti":"303260","tc":"Русе","wi":15.86,"pi":"1482","mi":"C","v":10585,"sc":1,"cc":1,"lpe":0.0,"lpr":202.68,"lq":51.86,"spr":200.0,"sq":68.63,"sb":2.82},{"ci":"303253","ri":"303254","ti":"422496","tc":"Сливен","wi":13.49,"pi":"1482","mi":"D","v":5072,"sc":2,"cc":2,"lpe":0.0,"lpr":126.25,"lq":14.32,"spr":198.94,"sq":20.23,"sb":1.4},{"ci":"303253","ri":"303254","ti":"303255","tc":"София","wi":22.55,"pi":"1482","mi":"D","v":204231,"sc":8,"cc":5,"lpe":20.7,"lpr":182.32,"lq":75.31,"spr":471.38,"sq":91.69,"sb":2.04},{"ci":"303253","ri":"303254","ti":"303259","tc":"Стара-Загора","wi":16.6,"pi":"1482","mi":"D","v":22972,"sc":3,"cc":3,"lpe":13.75,"lpr":183.88,"lq":58.64,"spr":142.14,"sq":70.4,"sb":1.72},{"ci":"15904","ri":"15916","ti":"15936","tc":"Бирмингем","wi":34.7,"pi":"1482","mi":"C","v":307061,"sc":9,"cc":8,"lpe":0.0,"lpr":330.22,"lq":56.71,"spr":272.58,"sq":84.75,"sb":0.4},{"ci":"15904","ri":"15916","ti":"422981","tc":"Брадфорд","wi":34.66,"pi":"1482","mi":"E","v":63433,"sc":1,"cc":1,"lpe":98.13,"lpr":627.83,"lq":1.0,"spr":627.31,"sq":2.95,"sb":0.0},{"ci":"15904","ri":"15916","ti":"352886","tc":"Бристоль","wi":38.04,"pi":"1482","mi":"D","v":25102,"sc":4,"cc":2,"lpe":0.0,"lpr":351.77,"lq":45.06,"spr":364.66,"sq":62.59,"sb":0.89},{"ci":"15904","ri":"15916","ti":"422514","tc":"Йорк","wi":35.25,"pi":"1482","mi":"AA","v":18561,"sc":2,"cc":2,"lpe":0.0,"lpr":473.9,"lq":27.25,"spr":371.76,"sq":87.91,"sb":0.11},{"ci":"15904","ri":"15916","ti":"375138","tc":"Лестер","wi":26.41,"pi":"1482","mi":"E","v":33452,"sc":3,"cc":3,"lpe":86.81,"lpr":252.63,"lq":35.52,"spr":298.33,"sq":39.33,"sb":0.13},{"ci":"15904","ri":"15916","ti":"373539","tc":"Ливерпуль","wi":45.56,"pi":"1482","mi":"E","v":26793,"sc":3,"cc":3,"lpe":46.41,"lpr":354.11,"lq":51.68,"spr":363.18,"sq":61.69,"sb":0.45},{"ci":"15904","ri":"15916","ti":"15938","tc":"Лидс","wi":42.81,"pi":"1482","mi":"E","v":39270,"sc":1,"cc":1,"lpe":87.13,"lpr":1394.96,"lq":1.08,"spr":1357.01,"sq":14.46,"sb":0.0},{"ci":"15904","ri":"15916","ti":"15935","tc":"Лондон","wi":37.45,"pi":"1482","mi":"C","v":625361,"sc":14,"cc":9,"lpe":0.0,"lpr":354.06,"lq":81.0,"spr":760.35,"sq":123.26,"sb":3.39},{"ci":"15904","ri":"15916","ti":"422941","tc":"Лоустофт","wi":25.71,"pi":"1482","mi":"D","v":6071,"sc":1,"cc":1,"lpe":14.2,"lpr":460.23,"lq":2.21,"spr":555.27,"sq":65.56,"sb":0.0},{"ci":"15904","ri":"15916","ti":"15941","tc":"Манчестер","wi":37.59,"pi":"1482","mi":"C","v":193118,"sc":3,"cc":3,"lpe":0.0,"lpr":592.26,"lq":1.39,"spr":800.47,"sq":69.8,"sb":1.92},{"ci":"15904","ri":"15916","ti":"348029","tc":"Шеффилд","wi":51.89,"pi":"1482","mi":"D","v":42528,"sc":5,"cc":4,"lpe":18.35,"lpr":366.34,"lq":45.89,"spr":427.44,"sq":68.07,"sb":2.17},{"ci":"375142","ri":"375143","ti":"375147","tc":"Баркисимето","wi":21.79,"pi":"1482","mi":"D","v":60662,"sc":1,"cc":1,"lpe":39.88,"lpr":208.2,"lq":73.42,"spr":563.98,"sq":105.18,"sb":2.42},{"ci":"375142","ri":"375143","ti":"375151","tc":"Барселона (Ve)","wi":13.01,"pi":"1482","mi":"B","v":35543,"sc":2,"cc":2,"lpe":0.0,"lpr":79.7,"lq":56.38,"spr":166.24,"sq":88.25,"sb":0.0},{"ci":"375142","ri":"375143","ti":"375146","tc":"Валенсия (Ve)","wi":24.0,"pi":"1482","mi":"C","v":75347,"sc":4,"cc":4,"lpe":0.0,"lpr":232.23,"lq":81.51,"spr":646.0,"sq":122.62,"sb":2.96},{"ci":"375142","ri":"375143","ti":"375144","tc":"Каракас","wi":31.28,"pi":"1482","mi":"B","v":177188,"sc":3,"cc":3,"lpe":0.0,"lpr":448.44,"lq":75.7,"spr":494.26,"sq":108.42,"sb":5.55},{"ci":"375142","ri":"375143","ti":"375149","tc":"Маракай","wi":14.16,"pi":"1482","mi":"E","v":41000,"sc":1,"cc":1,"lpe":87.13,"lpr":178.56,"lq":40.96,"spr":258.56,"sq":52.23,"sb":0.52},{"ci":"375142","ri":"375143","ti":"375145","tc":"Маракайбо","wi":21.64,"pi":"1482","mi":"C","v":81409,"sc":4,"cc":4,"lpe":0.0,"lpr":221.87,"lq":78.08,"spr":630.91,"sq":119.14,"sb":4.66},{"ci":"375142","ri":"375143","ti":"375150","tc":"Матурин","wi":14.91,"pi":"1482","mi":"D","v":29776,"sc":2,"cc":2,"lpe":27.81,"lpr":173.16,"lq":37.63,"spr":254.93,"sq":59.17,"sb":0.33},{"ci":"375142","ri":"375143","ti":"375148","tc":"Сьюдад-Гуаяна","wi":21.1,"pi":"1482","mi":"D","v":48976,"sc":4,"cc":4,"lpe":22.98,"lpr":212.4,"lq":77.87,"spr":550.07,"sq":108.45,"sb":2.27},{"ci":"15905","ri":"3042","ti":"3043","tc":"Берлин","wi":32.83,"pi":"1482","mi":"A","v":286378,"sc":9,"cc":7,"lpe":0.0,"lpr":671.15,"lq":83.22,"spr":752.13,"sq":125.05,"sb":3.74},{"ci":"15905","ri":"3042","ti":"15955","tc":"Бонн","wi":41.0,"pi":"1482","mi":"A","v":75648,"sc":3,"cc":3,"lpe":0.0,"lpr":279.95,"lq":34.52,"spr":570.88,"sq":89.6,"sb":4.74},{"ci":"15905","ri":"3042","ti":"3052","tc":"Бремен","wi":45.89,"pi":"1482","mi":"A","v":95782,"sc":2,"cc":2,"lpe":0.0,"lpr":264.34,"lq":83.62,"spr":800.0,"sq":129.01,"sb":4.25},{"ci":"15905","ri":"3042","ti":"422980","tc":"Вупперталь","wi":28.16,"pi":"1482","mi":"E","v":41744,"sc":2,"cc":2,"lpe":58.15,"lpr":312.0,"lq":1.85,"spr":258.77,"sq":18.52,"sb":0.0},{"ci":"15905","ri":"3042","ti":"3044","tc":"Гамбург","wi":38.62,"pi":"1482","mi":"A","v":238606,"sc":6,"cc":4,"lpe":0.0,"lpr":449.72,"lq":83.21,"spr":764.84,"sq":121.52,"sb":3.77},{"ci":"15905","ri":"3042","ti":"3053","tc":"Ганновер","wi":40.08,"pi":"1482","mi":"A","v":70132,"sc":4,"cc":2,"lpe":0.0,"lpr":205.09,"lq":96.14,"spr":800.0,"sq":126.56,"sb":4.25},{"ci":"15905","ri":"3042","ti":"3049","tc":"Дортмунд","wi":33.41,"pi":"1482","mi":"B","v":66643,"sc":4,"cc":2,"lpe":0.0,"lpr":193.8,"lq":94.95,"spr":800.0,"sq":126.51,"sb":4.25},{"ci":"15905","ri":"3042","ti":"15957","tc":"Дрезден","wi":27.07,"pi":"1482","mi":"D","v":47196,"sc":3,"cc":2,"lpe":31.57,"lpr":222.5,"lq":70.67,"spr":617.69,"sq":108.78,"sb":2.91},{"ci":"15905","ri":"3042","ti":"3051","tc":"Дюссельдорф","wi":30.07,"pi":"1482","mi":"B","v":66531,"sc":4,"cc":2,"lpe":0.0,"lpr":196.43,"lq":95.06,"spr":800.0,"sq":128.04,"sb":4.25},{"ci":"15905","ri":"3042","ti":"422492","tc":"Карлсруэ","wi":47.97,"pi":"1482","mi":"A","v":36999,"sc":2,"cc":2,"lpe":0.0,"lpr":746.95,"lq":33.94,"spr":699.39,"sq":125.45,"sb":3.63},{"ci":"15905","ri":"3042","ti":"422977","tc":"Киль","wi":27.65,"pi":"1482","mi":"E","v":29351,"sc":1,"cc":1,"lpe":93.19,"lpr":428.03,"lq":1.12,"spr":429.53,"sq":8.2,"sb":0.0},{"ci":"15905","ri":"3042","ti":"3046","tc":"Кёльн","wi":34.99,"pi":"1482","mi":"A","v":109537,"sc":4,"cc":2,"lpe":0.0,"lpr":205.81,"lq":89.04,"spr":800.0,"sq":127.99,"sb":4.25},{"ci":"15905","ri":"3042","ti":"422529","tc":"Любек","wi":59.21,"pi":"1482","mi":"A","v":22217,"sc":1,"cc":1,"lpe":0.0,"lpr":279.5,"lq":29.84,"spr":800.0,"sq":129.01,"sb":4.25},{"ci":"15905","ri":"3042","ti":"3045","tc":"Мюнхен","wi":22.99,"pi":"1482","mi":"D","v":160623,"sc":4,"cc":2,"lpe":10.54,"lpr":187.16,"lq":82.88,"spr":735.41,"sq":123.2,"sb":3.8},{"ci":"15905","ri":"3042","ti":"15954","tc":"Нюрнберг","wi":33.83,"pi":"1482","mi":"A","v":80461,"sc":3,"cc":2,"lpe":0.0,"lpr":232.76,"lq":66.03,"spr":496.77,"sq":89.74,"sb":4.7},{"ci":"15905","ri":"3042","ti":"422022","tc":"Потсдам","wi":30.75,"pi":"1482","mi":"B","v":14842,"sc":3,"cc":3,"lpe":0.0,"lpr":331.77,"lq":58.76,"spr":737.25,"sq":122.0,"sb":4.06},{"ci":"15905","ri":"3042","ti":"3047","tc":"Франкфурт","wi":45.7,"pi":"1482","mi":"A","v":171444,"sc":5,"cc":3,"lpe":0.0,"lpr":250.07,"lq":85.94,"spr":797.68,"sq":128.69,"sb":4.25},{"ci":"15905","ri":"3042","ti":"3050","tc":"Штутгарт","wi":26.36,"pi":"1482","mi":"D","v":87311,"sc":4,"cc":3,"lpe":14.64,"lpr":188.91,"lq":82.39,"spr":643.49,"sq":117.9,"sb":3.22},{"ci":"15905","ri":"3042","ti":"422493","tc":"Эбербах","wi":26.53,"pi":"1482","mi":"E","v":1307,"sc":1,"cc":1,"lpe":52.95,"lpr":351.53,"lq":33.23,"spr":562.55,"sq":78.3,"sb":2.0},{"ci":"15905","ri":"3042","ti":"3048","tc":"Эссен","wi":24.84,"pi":"1482","mi":"B","v":122519,"sc":4,"cc":3,"lpe":0.0,"lpr":217.02,"lq":82.08,"spr":755.11,"sq":125.12,"sb":3.87},{"ci":"422043","ri":"422044","ti":"422046","tc":"Афины","wi":25.14,"pi":"1482","mi":"D","v":109035,"sc":6,"cc":5,"lpe":0.0,"lpr":387.43,"lq":76.91,"spr":752.23,"sq":123.71,"sb":3.78},{"ci":"422043","ri":"422044","ti":"422051","tc":"Волос","wi":10.11,"pi":"1482","mi":"D","v":10043,"sc":3,"cc":2,"lpe":16.13,"lpr":173.73,"lq":25.58,"spr":189.62,"sq":81.22,"sb":0.5},{"ci":"422043","ri":"422044","ti":"422050","tc":"Ларисса","wi":11.25,"pi":"1482","mi":"E","v":8404,"sc":3,"cc":3,"lpe":69.95,"lpr":526.31,"lq":2.28,"spr":613.5,"sq":33.14,"sb":0.0},{"ci":"422043","ri":"422044","ti":"422495","tc":"Пирей","wi":16.29,"pi":"1482","mi":"E","v":7170,"sc":1,"cc":1,"lpe":86.6,"lpr":809.24,"lq":2.34,"spr":888.42,"sq":16.08,"sb":0.0},{"ci":"422043","ri":"422044","ti":"422047","tc":"Салоники","wi":19.42,"pi":"1482","mi":"D","v":44610,"sc":8,"cc":7,"lpe":43.4,"lpr":274.26,"lq":76.14,"spr":511.58,"sq":100.84,"sb":1.84},{"ci":"422043","ri":"422045","ti":"422049","tc":"Ираклион","wi":13.1,"pi":"1482","mi":"E","v":13363,"sc":5,"cc":4,"lpe":77.4,"lpr":318.54,"lq":2.1,"spr":319.54,"sq":23.16,"sb":0.05},{"ci":"422043","ri":"422045","ti":"422048","tc":"Патры","wi":12.75,"pi":"1482","mi":"E","v":8693,"sc":3,"cc":3,"lpe":76.19,"lpr":268.93,"lq":22.24,"spr":299.91,"sq":40.2,"sb":0.0},{"ci":"422043","ri":"422045","ti":"422997","tc":"Родос","wi":10.41,"pi":"1482","mi":"E","v":11334,"sc":1,"cc":1,"lpe":85.89,"lpr":200.14,"lq":1.18,"spr":214.23,"sq":15.83,"sb":0.0},{"ci":"422043","ri":"422045","ti":"422515","tc":"Спарта","wi":10.19,"pi":"1482","mi":"C","v":2265,"sc":3,"cc":3,"lpe":0.0,"lpr":133.33,"lq":17.22,"spr":249.72,"sq":104.63,"sb":0.0},{"ci":"422043","ri":"422045","ti":"422052","tc":"Ханья","wi":12.57,"pi":"1482","mi":"D","v":8571,"sc":2,"cc":2,"lpe":46.8,"lpr":96.91,"lq":31.04,"spr":155.02,"sq":53.23,"sb":0.94},{"ci":"7060","ri":"7064","ti":"422505","tc":"Зыряновск","wi":8.86,"pi":"1482","mi":"E","v":9540,"sc":1,"cc":1,"lpe":91.98,"lpr":101.02,"lq":1.85,"spr":112.97,"sq":3.17,"sb":0.0},{"ci":"7060","ri":"7064","ti":"422507","tc":"Риддер","wi":11.64,"pi":"1482","mi":"E","v":12620,"sc":2,"cc":2,"lpe":88.21,"lpr":140.03,"lq":7.39,"spr":152.98,"sq":8.88,"sb":0.0},{"ci":"7060","ri":"7064","ti":"7083","tc":"Семипалатинск","wi":11.27,"pi":"1482","mi":"E","v":55812,"sc":1,"cc":1,"lpe":66.4,"lpr":96.52,"lq":10.93,"spr":148.09,"sq":25.29,"sb":0.01},{"ci":"7060","ri":"7064","ti":"7082","tc":"Усть-Каменогорск","wi":10.56,"pi":"1482","mi":"C","v":28495,"sc":4,"cc":3,"lpe":0.0,"lpr":130.59,"lq":9.87,"spr":328.6,"sq":40.08,"sb":4.22},{"ci":"7060","ri":"7065","ti":"7087","tc":"Актау","wi":10.97,"pi":"1482","mi":"D","v":21500,"sc":3,"cc":3,"lpe":40.29,"lpr":217.55,"lq":30.95,"spr":173.93,"sq":38.13,"sb":0.05},{"ci":"7060","ri":"7065","ti":"7084","tc":"Актобе","wi":11.69,"pi":"1482","mi":"D","v":29900,"sc":3,"cc":3,"lpe":46.46,"lpr":221.88,"lq":57.81,"spr":206.13,"sq":71.07,"sb":0.08},{"ci":"7060","ri":"7065","ti":"7086","tc":"Атырау","wi":10.55,"pi":"1482","mi":"E","v":28583,"sc":2,"cc":2,"lpe":63.96,"lpr":124.93,"lq":38.23,"spr":243.38,"sq":44.08,"sb":0.0},{"ci":"7060","ri":"7065","ti":"422526","tc":"Жанаозен","wi":13.47,"pi":"1482","mi":"E","v":9750,"sc":1,"cc":1,"lpe":67.18,"lpr":154.87,"lq":31.26,"spr":130.3,"sq":35.62,"sb":0.0},{"ci":"7060","ri":"7065","ti":"7085","tc":"Уральск","wi":9.65,"pi":"1482","mi":"E","v":28238,"sc":2,"cc":2,"lpe":61.74,"lpr":189.94,"lq":27.26,"spr":209.88,"sq":29.03,"sb":0.07},{"ci":"7060","ri":"7062","ti":"7073","tc":"Астана","wi":18.37,"pi":"1482","mi":"E","v":60278,"sc":3,"cc":3,"lpe":86.59,"lpr":533.13,"lq":46.84,"spr":482.25,"sq":46.73,"sb":0.0},{"ci":"7060","ri":"7062","ti":"7071","tc":"Кокшетау","wi":12.69,"pi":"1482","mi":"C","v":22894,"sc":5,"cc":5,"lpe":0.0,"lpr":157.93,"lq":42.81,"spr":113.41,"sq":53.8,"sb":0.22},{"ci":"7060","ri":"7062","ti":"7069","tc":"Костанай","wi":9.03,"pi":"1482","mi":"E","v":45560,"sc":2,"cc":2,"lpe":89.92,"lpr":147.58,"lq":1.02,"spr":171.41,"sq":5.25,"sb":0.12},{"ci":"7060","ri":"7062","ti":"7072","tc":"Павлодар","wi":14.85,"pi":"1482","mi":"E","v":27738,"sc":1,"cc":1,"lpe":86.49,"lpr":664.44,"lq":4.13,"spr":763.83,"sq":8.84,"sb":0.0},{"ci":"7060","ri":"7062","ti":"7070","tc":"Петропавловск","wi":2.93,"pi":"1482","mi":"E","v":265722,"sc":1,"cc":1,"lpe":99.25,"lpr":35.02,"lq":1.0,"spr":35.01,"sq":1.31,"sb":0.02},{"ci":"7060","ri":"7062","ti":"7075","tc":"Рудный","wi":9.74,"pi":"1482","mi":"E","v":38933,"sc":3,"cc":3,"lpe":58.6,"lpr":149.82,"lq":39.86,"spr":115.35,"sq":41.42,"sb":0.05},{"ci":"7060","ri":"7062","ti":"7074","tc":"Экибастуз","wi":12.31,"pi":"1482","mi":"D","v":21912,"sc":2,"cc":2,"lpe":0.0,"lpr":172.48,"lq":34.87,"spr":176.08,"sq":49.76,"sb":0.65},{"ci":"7060","ri":"7061","ti":"7068","tc":"Жезказган","wi":6.48,"pi":"1482","mi":"E","v":20341,"sc":3,"cc":3,"lpe":52.49,"lpr":42.2,"lq":23.39,"spr":69.71,"sq":38.12,"sb":0.01},{"ci":"7060","ri":"7061","ti":"7066","tc":"Караганда","wi":19.29,"pi":"1482","mi":"E","v":83751,"sc":3,"cc":2,"lpe":88.65,"lpr":324.62,"lq":60.26,"spr":309.28,"sq":61.09,"sb":0.23},{"ci":"7060","ri":"7061","ti":"7067","tc":"Темиртау","wi":15.01,"pi":"1482","mi":"E","v":20288,"sc":1,"cc":1,"lpe":100.0,"lpr":305.12,"lq":43.68,"spr":305.11,"sq":43.68,"sb":0.0},{"ci":"7060","ri":"7063","ti":"7076","tc":"Алматы","wi":17.91,"pi":"1482","mi":"E","v":121271,"sc":4,"cc":3,"lpe":50.01,"lpr":322.29,"lq":34.25,"spr":293.21,"sq":43.39,"sb":0.02},{"ci":"7060","ri":"7063","ti":"7081","tc":"Байконур","wi":6.32,"pi":"1482","mi":"E","v":40173,"sc":2,"cc":2,"lpe":60.33,"lpr":69.64,"lq":24.72,"spr":113.29,"sq":29.62,"sb":0.0},{"ci":"7060","ri":"7063","ti":"7080","tc":"Кызылорда","wi":10.41,"pi":"1482","mi":"E","v":16264,"sc":1,"cc":1,"lpe":69.26,"lpr":160.81,"lq":31.48,"spr":142.12,"sq":35.5,"sb":0.0},{"ci":"7060","ri":"7063","ti":"7079","tc":"Талдыкорган","wi":9.41,"pi":"1482","mi":"D","v":8332,"sc":6,"cc":6,"lpe":42.49,"lpr":402.87,"lq":4.23,"spr":281.5,"sq":20.87,"sb":0.95},{"ci":"7060","ri":"7063","ti":"7078","tc":"Тараз","wi":4.87,"pi":"1482","mi":"E","v":28954,"sc":3,"cc":3,"lpe":64.15,"lpr":102.61,"lq":4.51,"spr":93.18,"sq":18.8,"sb":0.0},{"ci":"7060","ri":"7063","ti":"7077","tc":"Шымкент","wi":11.46,"pi":"1482","mi":"E","v":50676,"sc":2,"cc":2,"lpe":90.13,"lpr":112.7,"lq":27.24,"spr":111.45,"sq":28.95,"sb":0.0},{"ci":"422362","ri":"422363","ti":"422373","tc":"Гамильтон","wi":23.63,"pi":"1482","mi":"D","v":38907,"sc":2,"cc":2,"lpe":12.68,"lpr":236.78,"lq":48.72,"spr":548.46,"sq":105.08,"sb":1.59},{"ci":"422362","ri":"422363","ti":"422371","tc":"Квебек","wi":27.58,"pi":"1482","mi":"B","v":54989,"sc":4,"cc":4,"lpe":0.0,"lpr":231.66,"lq":50.01,"spr":504.67,"sq":107.59,"sb":1.3},{"ci":"422362","ri":"422363","ti":"422366","tc":"Монреаль","wi":29.1,"pi":"1482","mi":"B","v":251575,"sc":5,"cc":5,"lpe":0.0,"lpr":358.41,"lq":49.92,"spr":747.91,"sq":109.92,"sb":2.59},{"ci":"422362","ri":"422363","ti":"422369","tc":"Оттава","wi":19.37,"pi":"1482","mi":"B","v":55548,"sc":7,"cc":7,"lpe":0.0,"lpr":203.94,"lq":49.63,"spr":474.32,"sq":109.23,"sb":2.23},{"ci":"422362","ri":"422363","ti":"422365","tc":"Торонто","wi":28.32,"pi":"1482","mi":"C","v":367592,"sc":9,"cc":9,"lpe":0.0,"lpr":357.46,"lq":48.97,"spr":453.31,"sq":110.61,"sb":4.48},{"ci":"422362","ri":"422364","ti":"422367","tc":"Ванкувер","wi":25.17,"pi":"1482","mi":"B","v":127059,"sc":1,"cc":1,"lpe":0.0,"lpr":316.16,"lq":49.99,"spr":800.0,"sq":129.01,"sb":4.59},{"ci":"422362","ri":"422364","ti":"422372","tc":"Виннипег","wi":21.16,"pi":"1482","mi":"D","v":32694,"sc":2,"cc":2,"lpe":25.27,"lpr":250.56,"lq":48.92,"spr":660.0,"sq":107.72,"sb":3.41},{"ci":"422362","ri":"422364","ti":"422368","tc":"Калгари","wi":23.21,"pi":"1482","mi":"B","v":73274,"sc":1,"cc":1,"lpe":0.0,"lpr":286.87,"lq":50.84,"spr":800.0,"sq":129.01,"sb":4.59},{"ci":"422362","ri":"422364","ti":"422370","tc":"Эдмонтон","wi":23.41,"pi":"1482","mi":"D","v":64489,"sc":1,"cc":1,"lpe":32.33,"lpr":261.54,"lq":49.93,"spr":625.91,"sq":102.31,"sb":3.11},{"ci":"422187","ri":"422188","ti":"422942","tc":"Баямо","wi":11.5,"pi":"1482","mi":"E","v":12529,"sc":1,"cc":1,"lpe":80.05,"lpr":270.22,"lq":1.09,"spr":286.14,"sq":21.83,"sb":0.0},{"ci":"422187","ri":"422188","ti":"422189","tc":"Гавана","wi":20.27,"pi":"1482","mi":"E","v":99099,"sc":9,"cc":9,"lpe":79.44,"lpr":230.09,"lq":54.74,"spr":222.82,"sq":60.81,"sb":0.0},{"ci":"422187","ri":"422188","ti":"422193","tc":"Гуантанамо","wi":22.11,"pi":"1482","mi":"D","v":11471,"sc":2,"cc":2,"lpe":0.0,"lpr":212.44,"lq":49.86,"spr":305.97,"sq":70.84,"sb":0.83},{"ci":"422187","ri":"422188","ti":"422191","tc":"Камагуэй","wi":12.63,"pi":"1482","mi":"E","v":26693,"sc":2,"cc":2,"lpe":91.28,"lpr":148.83,"lq":1.0,"spr":157.65,"sq":7.02,"sb":0.0},{"ci":"422187","ri":"422188","ti":"422979","tc":"Лас Тунас","wi":10.87,"pi":"1482","mi":"E","v":20177,"sc":1,"cc":1,"lpe":85.13,"lpr":265.03,"lq":1.09,"spr":273.2,"sq":16.55,"sb":0.0},{"ci":"422187","ri":"422188","ti":"422192","tc":"Ольгин","wi":10.78,"pi":"1482","mi":"E","v":45542,"sc":2,"cc":2,"lpe":93.77,"lpr":229.68,"lq":1.0,"spr":232.85,"sq":5.7,"sb":0.06},{"ci":"422187","ri":"422188","ti":"422195","tc":"Пинар-дель-Рио","wi":10.41,"pi":"1482","mi":"A","v":20135,"sc":3,"cc":3,"lpe":0.0,"lpr":78.79,"lq":15.0,"spr":95.11,"sq":32.3,"sb":2.86},{"ci":"422187","ri":"422188","ti":"422194","tc":"Санта-Клара","wi":12.37,"pi":"1482","mi":"E","v":10437,"sc":2,"cc":2,"lpe":83.45,"lpr":192.58,"lq":48.97,"spr":193.65,"sq":52.35,"sb":0.21},{"ci":"422187","ri":"422188","ti":"422190","tc":"Сантьяго-де-Куба","wi":18.52,"pi":"1482","mi":"E","v":40388,"sc":3,"cc":3,"lpe":54.28,"lpr":141.55,"lq":36.88,"spr":235.53,"sq":53.32,"sb":1.7},{"ci":"325645","ri":"325646","ti":"422943","tc":"Вентспилс","wi":16.73,"pi":"1482","mi":"E","v":2887,"sc":1,"cc":1,"lpe":71.25,"lpr":245.16,"lq":2.94,"spr":289.68,"sq":17.75,"sb":0.0},{"ci":"325645","ri":"325646","ti":"325648","tc":"Даугавпилс","wi":16.09,"pi":"1482","mi":"E","v":23434,"sc":3,"cc":3,"lpe":64.06,"lpr":222.61,"lq":53.5,"spr":207.74,"sq":61.69,"sb":0.29},{"ci":"325645","ri":"325646","ti":"422513","tc":"Елгава","wi":11.6,"pi":"1482","mi":"E","v":3192,"sc":1,"cc":1,"lpe":96.87,"lpr":276.15,"lq":3.94,"spr":272.81,"sq":3.89,"sb":0.02},{"ci":"325645","ri":"325646","ti":"325649","tc":"Лиепая","wi":23.15,"pi":"1482","mi":"E","v":9510,"sc":1,"cc":1,"lpe":63.44,"lpr":350.36,"lq":63.55,"spr":295.39,"sq":72.28,"sb":0.06},{"ci":"325645","ri":"325646","ti":"325647","tc":"Рига","wi":25.75,"pi":"1482","mi":"C","v":74796,"sc":14,"cc":10,"lpe":0.0,"lpr":485.02,"lq":48.82,"spr":423.57,"sq":71.06,"sb":1.03},{"ci":"325645","ri":"325646","ti":"422037","tc":"Юрмала","wi":23.9,"pi":"1482","mi":"D","v":2982,"sc":4,"cc":4,"lpe":0.0,"lpr":607.03,"lq":24.14,"spr":509.47,"sq":81.41,"sb":0.11},{"ci":"325650","ri":"325651","ti":"325652","tc":"Вильнюс","wi":29.5,"pi":"1482","mi":"D","v":41681,"sc":6,"cc":5,"lpe":45.63,"lpr":451.52,"lq":49.57,"spr":432.16,"sq":60.88,"sb":0.57},{"ci":"325650","ri":"325651","ti":"325653","tc":"Каунас","wi":20.92,"pi":"1482","mi":"E","v":42185,"sc":4,"cc":3,"lpe":92.19,"lpr":168.45,"lq":36.74,"spr":164.95,"sq":39.21,"sb":0.11},{"ci":"325650","ri":"325651","ti":"325654","tc":"Клайпеда","wi":18.5,"pi":"1482","mi":"E","v":12183,"sc":3,"cc":3,"lpe":76.2,"lpr":419.89,"lq":23.19,"spr":475.58,"sq":27.21,"sb":1.28},{"ci":"325650","ri":"325651","ti":"422940","tc":"Шауляй","wi":23.77,"pi":"1482","mi":"","v":8240,"sc":0,"cc":0,"lpe":100.0,"lpr":778.22,"lq":1.0,"spr":778.22,"sq":1.0,"sb":0.0},{"ci":"422607","ri":"422608","ti":"422633","tc":"Гуадалупе","wi":17.48,"pi":"1482","mi":"D","v":25882,"sc":3,"cc":3,"lpe":47.0,"lpr":222.83,"lq":16.21,"spr":497.29,"sq":70.43,"sb":1.83},{"ci":"422607","ri":"422608","ti":"422629","tc":"Кульякан","wi":7.91,"pi":"1482","mi":"D","v":27034,"sc":2,"cc":2,"lpe":38.15,"lpr":64.6,"lq":7.34,"spr":109.23,"sq":20.63,"sb":0.03},{"ci":"422607","ri":"422608","ti":"422630","tc":"Мехикали","wi":7.54,"pi":"1482","mi":"E","v":26617,"sc":2,"cc":2,"lpe":73.9,"lpr":128.39,"lq":4.39,"spr":126.8,"sq":5.01,"sb":0.02},{"ci":"422607","ri":"422608","ti":"422620","tc":"Монтеррей","wi":24.29,"pi":"1482","mi":"D","v":47034,"sc":3,"cc":3,"lpe":13.11,"lpr":256.45,"lq":27.91,"spr":719.12,"sq":112.89,"sb":3.59},{"ci":"422607","ri":"422608","ti":"422627","tc":"Сальтильо","wi":23.59,"pi":"1482","mi":"E","v":29413,"sc":1,"cc":1,"lpe":53.85,"lpr":259.99,"lq":24.95,"spr":509.22,"sq":71.44,"sb":1.98},{"ci":"422607","ri":"422608","ti":"422616","tc":"Сьюдад-Хуарес","wi":26.46,"pi":"1482","mi":"B","v":69687,"sc":4,"cc":4,"lpe":0.0,"lpr":244.95,"lq":29.58,"spr":505.54,"sq":110.43,"sb":1.47},{"ci":"422607","ri":"422608","ti":"422617","tc":"Тихуана","wi":29.36,"pi":"1482","mi":"A","v":68407,"sc":4,"cc":4,"lpe":0.0,"lpr":314.11,"lq":31.5,"spr":613.94,"sq":117.38,"sb":2.27},{"ci":"422607","ri":"422608","ti":"422622","tc":"Чиуауа","wi":7.08,"pi":"1482","mi":"E","v":42778,"sc":6,"cc":6,"lpe":80.25,"lpr":129.45,"lq":3.34,"spr":132.61,"sq":3.93,"sb":0.01},{"ci":"422607","ri":"422608","ti":"422625","tc":"Эрмосильо","wi":19.74,"pi":"1482","mi":"D","v":30040,"sc":3,"cc":2,"lpe":28.4,"lpr":208.85,"lq":25.38,"spr":390.85,"sq":72.06,"sb":0.87},{"ci":"422607","ri":"422609","ti":"422626","tc":"Агуаскальентес","wi":15.81,"pi":"1482","mi":"E","v":35383,"sc":2,"cc":2,"lpe":77.46,"lpr":192.72,"lq":1.0,"spr":304.16,"sq":24.55,"sb":0.82},{"ci":"422607","ri":"422609","ti":"422632","tc":"Акапулько","wi":30.24,"pi":"1482","mi":"B","v":33667,"sc":1,"cc":1,"lpe":0.0,"lpr":270.46,"lq":27.98,"spr":800.0,"sq":129.01,"sb":4.21},{"ci":"422607","ri":"422609","ti":"422614","tc":"Гвадалахара","wi":32.94,"pi":"1482","mi":"A","v":86689,"sc":5,"cc":5,"lpe":0.0,"lpr":370.87,"lq":30.97,"spr":582.34,"sq":96.22,"sb":3.29},{"ci":"422607","ri":"422609","ti":"422618","tc":"Леон","wi":22.29,"pi":"1482","mi":"A","v":88328,"sc":3,"cc":3,"lpe":0.0,"lpr":284.62,"lq":31.14,"spr":392.65,"sq":88.25,"sb":3.21},{"ci":"422607","ri":"422609","ti":"422628","tc":"Сан-Луис-Потоси","wi":31.74,"pi":"1482","mi":"B","v":34338,"sc":2,"cc":2,"lpe":0.0,"lpr":278.38,"lq":29.24,"spr":798.55,"sq":128.8,"sb":4.2},{"ci":"422607","ri":"422609","ti":"422619","tc":"Сапопан","wi":16.25,"pi":"1482","mi":"C","v":47937,"sc":5,"cc":5,"lpe":0.0,"lpr":180.43,"lq":25.56,"spr":282.83,"sq":69.69,"sb":0.77},{"ci":"422607","ri":"422610","ti":"422612","tc":"Мехико","wi":32.07,"pi":"1482","mi":"B","v":545339,"sc":15,"cc":12,"lpe":0.0,"lpr":363.22,"lq":32.01,"spr":322.68,"sq":101.8,"sb":4.0},{"ci":"422607","ri":"422610","ti":"422623","tc":"Наукальпан","wi":30.88,"pi":"1482","mi":"B","v":43096,"sc":1,"cc":1,"lpe":0.0,"lpr":254.92,"lq":25.69,"spr":800.0,"sq":129.01,"sb":3.5},{"ci":"422607","ri":"422610","ti":"422621","tc":"Несауалькойотль","wi":32.26,"pi":"1482","mi":"B","v":108509,"sc":8,"cc":6,"lpe":0.0,"lpr":252.65,"lq":26.77,"spr":535.26,"sq":107.41,"sb":1.34},{"ci":"422607","ri":"422610","ti":"422615","tc":"Пуэбла-де-Сарагоса","wi":30.36,"pi":"1482","mi":"D","v":100677,"sc":8,"cc":6,"lpe":0.0,"lpr":257.71,"lq":30.6,"spr":534.69,"sq":110.83,"sb":1.48},{"ci":"422607","ri":"422610","ti":"422613","tc":"Экатепек-де-Морелос","wi":33.69,"pi":"1482","mi":"C","v":73145,"sc":2,"cc":2,"lpe":0.0,"lpr":380.6,"lq":30.4,"spr":799.98,"sq":129.01,"sb":3.5},{"ci":"422607","ri":"422611","ti":"422648","tc":"Виллахермоса","wi":33.44,"pi":"1482","mi":"E","v":14965,"sc":6,"cc":6,"lpe":77.34,"lpr":430.53,"lq":24.2,"spr":422.97,"sq":35.13,"sb":0.3},{"ci":"422607","ri":"422611","ti":"422631","tc":"Канкун","wi":16.33,"pi":"1482","mi":"E","v":31587,"sc":2,"cc":2,"lpe":74.25,"lpr":217.7,"lq":26.45,"spr":363.63,"sq":52.31,"sb":1.14},{"ci":"422607","ri":"422611","ti":"422624","tc":"Мерида","wi":15.42,"pi":"1482","mi":"E","v":61017,"sc":3,"cc":3,"lpe":74.89,"lpr":232.01,"lq":14.05,"spr":366.39,"sq":41.66,"sb":1.07},{"ci":"359837","ri":"359838","ti":"359845","tc":"Алмере","wi":17.61,"pi":"1482","mi":"D","v":16443,"sc":2,"cc":2,"lpe":31.39,"lpr":242.35,"lq":74.32,"spr":409.04,"sq":99.19,"sb":1.81},{"ci":"359837","ri":"359838","ti":"359839","tc":"Амстердам","wi":35.99,"pi":"1482","mi":"A","v":72597,"sc":1,"cc":1,"lpe":0.0,"lpr":929.16,"lq":83.93,"spr":800.0,"sq":129.01,"sb":4.73},{"ci":"359837","ri":"359838","ti":"359840","tc":"Гаага","wi":37.51,"pi":"1482","mi":"A","v":59178,"sc":1,"cc":1,"lpe":0.0,"lpr":976.33,"lq":47.3,"spr":800.0,"sq":129.01,"sb":4.73},{"ci":"359837","ri":"359838","ti":"359846","tc":"Гронинген","wi":28.38,"pi":"1482","mi":"B","v":14773,"sc":1,"cc":1,"lpe":0.0,"lpr":260.64,"lq":83.41,"spr":800.0,"sq":129.01,"sb":4.73},{"ci":"359837","ri":"359838","ti":"359844","tc":"Маастрихт","wi":21.64,"pi":"1482","mi":"D","v":20162,"sc":1,"cc":1,"lpe":48.6,"lpr":222.94,"lq":58.13,"spr":519.57,"sq":94.4,"sb":2.43},{"ci":"359837","ri":"359838","ti":"359841","tc":"Роттердам","wi":31.6,"pi":"1482","mi":"A","v":76911,"sc":2,"cc":2,"lpe":0.0,"lpr":261.76,"lq":83.61,"spr":771.83,"sq":127.08,"sb":4.36},{"ci":"359837","ri":"359838","ti":"359842","tc":"Утрехт","wi":28.61,"pi":"1482","mi":"A","v":41319,"sc":1,"cc":1,"lpe":0.0,"lpr":249.81,"lq":91.57,"spr":800.0,"sq":129.01,"sb":4.73},{"ci":"359837","ri":"359838","ti":"422074","tc":"Харлем","wi":24.02,"pi":"1482","mi":"D","v":8288,"sc":1,"cc":1,"lpe":0.0,"lpr":249.04,"lq":34.56,"spr":750.01,"sq":120.44,"sb":4.3},{"ci":"359837","ri":"359838","ti":"359843","tc":"Эйндховен","wi":24.4,"pi":"1482","mi":"D","v":24073,"sc":2,"cc":2,"lpe":0.0,"lpr":234.23,"lq":38.35,"spr":551.56,"sq":90.41,"sb":3.03},{"ci":"335165","ri":"335166","ti":"335168","tc":"Берген","wi":18.23,"pi":"1482","mi":"D","v":17902,"sc":2,"cc":2,"lpe":0.0,"lpr":432.01,"lq":46.39,"spr":274.92,"sq":62.17,"sb":1.89},{"ci":"335165","ri":"335166","ti":"335171","tc":"Берум","wi":15.84,"pi":"1482","mi":"A","v":23525,"sc":2,"cc":2,"lpe":0.0,"lpr":73.7,"lq":44.09,"spr":94.45,"sq":62.54,"sb":1.35},{"ci":"335165","ri":"335166","ti":"422021","tc":"Кристиансанн","wi":11.28,"pi":"1482","mi":"B","v":5019,"sc":2,"cc":2,"lpe":0.0,"lpr":356.89,"lq":41.58,"spr":149.89,"sq":56.82,"sb":0.0},{"ci":"335165","ri":"335166","ti":"335167","tc":"Осло","wi":25.14,"pi":"1482","mi":"E","v":35186,"sc":3,"cc":3,"lpe":53.14,"lpr":540.51,"lq":65.66,"spr":474.48,"sq":70.67,"sb":0.65},{"ci":"335165","ri":"335166","ti":"335169","tc":"Ставангер","wi":24.22,"pi":"1482","mi":"D","v":10234,"sc":2,"cc":2,"lpe":36.49,"lpr":265.74,"lq":46.29,"spr":387.66,"sq":58.9,"sb":0.92},{"ci":"335165","ri":"335166","ti":"335170","tc":"Тронхейм","wi":19.98,"pi":"1482","mi":"B","v":11000,"sc":1,"cc":1,"lpe":0.0,"lpr":413.03,"lq":46.95,"spr":263.0,"sq":64.31,"sb":1.87},{"ci":"15734","ri":"15735","ti":"16322","tc":"Бобруйск","wi":4.65,"pi":"1482","mi":"E","v":147879,"sc":3,"cc":3,"lpe":50.54,"lpr":24.62,"lq":8.81,"spr":39.63,"sq":28.86,"sb":0.01},{"ci":"15734","ri":"15735","ti":"15737","tc":"Брест","wi":8.65,"pi":"1482","mi":"D","v":34937,"sc":3,"cc":3,"lpe":49.92,"lpr":166.08,"lq":27.62,"spr":145.31,"sq":35.12,"sb":0.78},{"ci":"15734","ri":"15735","ti":"422521","tc":"Вилейка","wi":8.89,"pi":"1482","mi":"E","v":3165,"sc":1,"cc":1,"lpe":60.51,"lpr":145.0,"lq":28.63,"spr":126.04,"sq":51.85,"sb":0.0},{"ci":"15734","ri":"15735","ti":"15741","tc":"Витебск","wi":8.24,"pi":"1482","mi":"D","v":27614,"sc":4,"cc":4,"lpe":32.37,"lpr":80.99,"lq":7.16,"spr":131.41,"sq":24.58,"sb":1.74},{"ci":"15734","ri":"15735","ti":"15738","tc":"Гомель","wi":10.34,"pi":"1482","mi":"E","v":72301,"sc":4,"cc":4,"lpe":94.53,"lpr":341.12,"lq":1.0,"spr":335.43,"sq":1.36,"sb":0.01},{"ci":"15734","ri":"15735","ti":"15739","tc":"Гродно","wi":8.0,"pi":"1482","mi":"C","v":26963,"sc":3,"cc":3,"lpe":0.0,"lpr":134.78,"lq":30.22,"spr":140.42,"sq":75.15,"sb":0.23},{"ci":"15734","ri":"15735","ti":"15736","tc":"Минск","wi":12.2,"pi":"1482","mi":"E","v":231304,"sc":9,"cc":9,"lpe":71.99,"lpr":172.54,"lq":51.64,"spr":140.34,"sq":55.62,"sb":0.76},{"ci":"15734","ri":"15735","ti":"15740","tc":"Могилёв","wi":7.68,"pi":"1482","mi":"E","v":32879,"sc":4,"cc":4,"lpe":91.55,"lpr":159.63,"lq":3.21,"spr":159.16,"sq":6.19,"sb":0.01},{"ci":"2931","ri":"2961","ti":"366263","tc":"Биробиджан","wi":5.75,"pi":"1482","mi":"E","v":120945,"sc":2,"cc":2,"lpe":74.37,"lpr":41.87,"lq":12.57,"spr":46.75,"sq":21.19,"sb":0.01},{"ci":"2931","ri":"2961","ti":"2964","tc":"Владивосток","wi":3.77,"pi":"1482","mi":"E","v":244964,"sc":5,"cc":5,"lpe":85.96,"lpr":36.32,"lq":1.71,"spr":38.93,"sq":7.85,"sb":0.05},{"ci":"2931","ri":"2961","ti":"422543","tc":"Петропавловск-Камчатский","wi":11.7,"pi":"1482","mi":"A","v":15916,"sc":6,"cc":6,"lpe":0.0,"lpr":113.2,"lq":22.32,"spr":141.14,"sq":29.39,"sb":2.88},{"ci":"2931","ri":"2961","ti":"2962","tc":"Хабаровск","wi":9.72,"pi":"1482","mi":"E","v":74340,"sc":2,"cc":2,"lpe":58.3,"lpr":218.13,"lq":42.56,"spr":180.31,"sq":43.83,"sb":0.1},{"ci":"2931","ri":"2961","ti":"2963","tc":"Якутск","wi":6.39,"pi":"1482","mi":"C","v":31007,"sc":2,"cc":2,"lpe":0.0,"lpr":94.42,"lq":38.19,"spr":74.99,"sq":44.13,"sb":0.1},{"ci":"2931","ri":"2939","ti":"422530","tc":"Елабуга","wi":11.02,"pi":"1482","mi":"D","v":6211,"sc":2,"cc":2,"lpe":43.34,"lpr":70.85,"lq":8.39,"spr":143.48,"sq":28.2,"sb":0.0},{"ci":"2931","ri":"2939","ti":"2943","tc":"Казань","wi":9.83,"pi":"1482","mi":"C","v":103336,"sc":7,"cc":7,"lpe":0.0,"lpr":147.62,"lq":30.44,"spr":113.47,"sq":42.0,"sb":2.43},{"ci":"2931","ri":"2939","ti":"2940","tc":"Нижний Новгород","wi":16.06,"pi":"1482","mi":"C","v":75716,"sc":7,"cc":7,"lpe":0.0,"lpr":449.24,"lq":30.85,"spr":431.86,"sq":41.6,"sb":2.68},{"ci":"2931","ri":"2939","ti":"2944","tc":"Пермь","wi":3.69,"pi":"1482","mi":"E","v":175567,"sc":6,"cc":5,"lpe":83.88,"lpr":42.1,"lq":12.25,"spr":41.31,"sq":14.54,"sb":0.04},{"ci":"2931","ri":"2939","ti":"2941","tc":"Самара","wi":5.03,"pi":"1482","mi":"E","v":87870,"sc":6,"cc":6,"lpe":52.47,"lpr":74.3,"lq":17.8,"spr":85.89,"sq":30.36,"sb":0.05},{"ci":"2931","ri":"2939","ti":"2942","tc":"Уфа","wi":9.19,"pi":"1482","mi":"E","v":197860,"sc":8,"cc":8,"lpe":65.2,"lpr":149.76,"lq":50.29,"spr":137.26,"sq":61.48,"sb":0.04},{"ci":"2931","ri":"331858","ti":"331860","tc":"Архангельск","wi":10.18,"pi":"1482","mi":"D","v":53947,"sc":3,"cc":3,"lpe":29.48,"lpr":133.02,"lq":41.57,"spr":130.89,"sq":66.82,"sb":0.0},{"ci":"2931","ri":"331858","ti":"331870","tc":"Великие Луки","wi":1.98,"pi":"1482","mi":"E","v":1239507,"sc":6,"cc":6,"lpe":83.29,"lpr":29.24,"lq":6.81,"spr":29.31,"sq":9.25,"sb":0.0},{"ci":"2931","ri":"331858","ti":"331866","tc":"Великий Новгород","wi":4.5,"pi":"1482","mi":"D","v":13900,"sc":2,"cc":2,"lpe":15.32,"lpr":152.28,"lq":28.66,"spr":95.72,"sq":33.75,"sb":0.0},{"ci":"2931","ri":"331858","ti":"331864","tc":"Вологда","wi":10.3,"pi":"1482","mi":"E","v":24892,"sc":3,"cc":3,"lpe":83.45,"lpr":250.04,"lq":2.7,"spr":262.18,"sq":7.18,"sb":0.0},{"ci":"2931","ri":"331858","ti":"331872","tc":"Воркута","wi":3.65,"pi":"1482","mi":"E","v":6151,"sc":1,"cc":1,"lpe":66.14,"lpr":26.36,"lq":10.29,"spr":64.84,"sq":24.01,"sb":1.97},{"ci":"2931","ri":"331858","ti":"331873","tc":"Выборг","wi":7.7,"pi":"1482","mi":"C","v":9088,"sc":1,"cc":1,"lpe":0.0,"lpr":139.89,"lq":20.47,"spr":14.5,"sq":49.68,"sb":0.0},{"ci":"2931","ri":"331858","ti":"331871","tc":"Гатчина","wi":14.24,"pi":"1482","mi":"E","v":8689,"sc":2,"cc":2,"lpe":90.38,"lpr":1239.46,"lq":1.0,"spr":1237.45,"sq":5.23,"sb":0.0},{"ci":"2931","ri":"331858","ti":"331859","tc":"Калининград","wi":16.61,"pi":"1482","mi":"E","v":59607,"sc":4,"cc":4,"lpe":73.89,"lpr":359.42,"lq":55.25,"spr":357.76,"sq":61.5,"sb":0.14},{"ci":"2931","ri":"331858","ti":"331862","tc":"Мурманск","wi":7.75,"pi":"1482","mi":"C","v":31299,"sc":3,"cc":3,"lpe":0.0,"lpr":285.82,"lq":3.19,"spr":298.32,"sq":19.66,"sb":0.05},{"ci":"2931","ri":"331858","ti":"331863","tc":"Петрозаводск","wi":10.69,"pi":"1482","mi":"B","v":17410,"sc":2,"cc":2,"lpe":0.0,"lpr":60.13,"lq":25.14,"spr":160.02,"sq":39.24,"sb":0.0},{"ci":"2931","ri":"331858","ti":"331867","tc":"Псков","wi":13.97,"pi":"1482","mi":"E","v":19238,"sc":1,"cc":1,"lpe":71.24,"lpr":337.47,"lq":6.48,"spr":528.02,"sq":26.52,"sb":0.0},{"ci":"2931","ri":"331858","ti":"2934","tc":"Санкт-Петербург","wi":16.62,"pi":"1482","mi":"E","v":333766,"sc":6,"cc":5,"lpe":90.07,"lpr":235.69,"lq":71.49,"spr":231.19,"sq":74.51,"sb":0.02},{"ci":"2931","ri":"331858","ti":"331868","tc":"Северодвинск","wi":3.84,"pi":"1482","mi":"E","v":13861,"sc":3,"cc":3,"lpe":93.36,"lpr":61.5,"lq":6.77,"spr":61.37,"sq":8.49,"sb":0.0},{"ci":"2931","ri":"331858","ti":"331865","tc":"Сыктывкар","wi":10.14,"pi":"1482","mi":"B","v":28359,"sc":2,"cc":2,"lpe":0.0,"lpr":129.38,"lq":21.33,"spr":54.59,"sq":30.83,"sb":0.01},{"ci":"2931","ri":"331858","ti":"331869","tc":"Ухта","wi":2.99,"pi":"1482","mi":"E","v":20493,"sc":2,"cc":2,"lpe":63.21,"lpr":18.32,"lq":5.32,"spr":30.75,"sq":11.05,"sb":0.24},{"ci":"2931","ri":"331858","ti":"331861","tc":"Череповец","wi":8.38,"pi":"1482","mi":"E","v":45534,"sc":1,"cc":1,"lpe":93.6,"lpr":231.97,"lq":1.08,"spr":267.04,"sq":5.37,"sb":0.15},{"ci":"2931","ri":"2956","ti":"371340","tc":"Иркутск","wi":16.65,"pi":"1482","mi":"B","v":73802,"sc":2,"cc":2,"lpe":0.0,"lpr":152.49,"lq":45.35,"spr":231.42,"sq":66.49,"sb":2.9},{"ci":"2931","ri":"2956","ti":"2960","tc":"Кемерово","wi":4.69,"pi":"1482","mi":"E","v":36473,"sc":2,"cc":2,"lpe":70.11,"lpr":25.02,"lq":11.94,"spr":39.37,"sq":25.44,"sb":0.59},{"ci":"2931","ri":"2956","ti":"2959","tc":"Красноярск","wi":17.22,"pi":"1482","mi":"E","v":75761,"sc":8,"cc":8,"lpe":94.24,"lpr":290.99,"lq":5.2,"spr":289.0,"sq":6.87,"sb":0.04},{"ci":"2931","ri":"2956","ti":"2957","tc":"Новосибирск","wi":11.87,"pi":"1482","mi":"C","v":178431,"sc":11,"cc":10,"lpe":0.0,"lpr":131.95,"lq":53.22,"spr":201.58,"sq":88.59,"sb":1.12},{"ci":"2931","ri":"2956","ti":"367967","tc":"Норильск","wi":3.91,"pi":"1482","mi":"E","v":18424,"sc":2,"cc":2,"lpe":92.09,"lpr":56.36,"lq":18.99,"spr":65.62,"sq":21.72,"sb":0.11},{"ci":"2931","ri":"2956","ti":"2958","tc":"Омск","wi":14.32,"pi":"1482","mi":"E","v":93144,"sc":6,"cc":6,"lpe":94.83,"lpr":657.75,"lq":1.0,"spr":660.91,"sq":4.45,"sb":0.01},{"ci":"2931","ri":"2956","ti":"10716","tc":"Томск","wi":8.53,"pi":"1482","mi":"E","v":58363,"sc":4,"cc":4,"lpe":98.61,"lpr":462.94,"lq":1.0,"spr":460.51,"sq":1.33,"sb":0.0},{"ci":"2931","ri":"2950","ti":"2951","tc":"Екатеринбург","wi":11.32,"pi":"1482","mi":"C","v":147019,"sc":7,"cc":6,"lpe":0.0,"lpr":84.45,"lq":54.81,"spr":118.74,"sq":81.28,"sb":0.16},{"ci":"2931","ri":"2950","ti":"422086","tc":"Курган","wi":14.93,"pi":"1482","mi":"E","v":18192,"sc":5,"cc":4,"lpe":60.36,"lpr":237.07,"lq":39.87,"spr":260.92,"sq":53.38,"sb":0.77},{"ci":"2931","ri":"2950","ti":"2954","tc":"Магнитогорск","wi":7.11,"pi":"1482","mi":"E","v":36062,"sc":5,"cc":4,"lpe":90.5,"lpr":151.74,"lq":1.0,"spr":151.61,"sq":3.92,"sb":0.01},{"ci":"2931","ri":"2950","ti":"2955","tc":"Сургут","wi":4.31,"pi":"1482","mi":"E","v":32245,"sc":4,"cc":3,"lpe":98.98,"lpr":104.06,"lq":1.0,"spr":104.23,"sq":1.04,"sb":0.0},{"ci":"2931","ri":"2950","ti":"2953","tc":"Тюмень","wi":5.19,"pi":"1482","mi":"E","v":42305,"sc":3,"cc":3,"lpe":61.69,"lpr":32.21,"lq":10.67,"spr":54.11,"sq":18.51,"sb":0.0},{"ci":"2931","ri":"2950","ti":"2952","tc":"Челябинск","wi":4.7,"pi":"1482","mi":"E","v":144196,"sc":10,"cc":8,"lpe":97.92,"lpr":129.03,"lq":1.0,"spr":127.18,"sq":1.27,"sb":0.0},{"ci":"2931","ri":"2932","ti":"2935","tc":"Воронеж","wi":4.59,"pi":"1482","mi":"D","v":60468,"sc":3,"cc":3,"lpe":11.94,"lpr":65.54,"lq":3.46,"spr":121.18,"sq":16.47,"sb":0.42},{"ci":"2931","ri":"2932","ti":"366651","tc":"Вышний Волочек","wi":3.63,"pi":"1482","mi":"E","v":5185,"sc":1,"cc":1,"lpe":50.59,"lpr":17.25,"lq":5.44,"spr":29.97,"sq":9.78,"sb":0.0},{"ci":"2931","ri":"2932","ti":"2938","tc":"Иваново","wi":3.44,"pi":"1482","mi":"D","v":56942,"sc":5,"cc":5,"lpe":35.73,"lpr":27.18,"lq":10.24,"spr":35.65,"sq":16.46,"sb":0.16},{"ci":"2931","ri":"2932","ti":"422085","tc":"Коломна","wi":3.68,"pi":"1482","mi":"E","v":8981,"sc":4,"cc":4,"lpe":85.75,"lpr":52.87,"lq":12.78,"spr":54.04,"sq":13.48,"sb":0.19},{"ci":"2931","ri":"2932","ti":"367968","tc":"Кострома","wi":16.13,"pi":"1482","mi":"E","v":33825,"sc":4,"cc":4,"lpe":60.06,"lpr":225.03,"lq":27.32,"spr":172.21,"sq":46.0,"sb":0.05},{"ci":"2931","ri":"2932","ti":"2937","tc":"Липецк","wi":10.02,"pi":"1482","mi":"E","v":51725,"sc":4,"cc":4,"lpe":85.08,"lpr":216.36,"lq":7.73,"spr":229.03,"sq":9.17,"sb":0.0},{"ci":"2931","ri":"2932","ti":"371339","tc":"Люберцы","wi":11.86,"pi":"1482","mi":"C","v":11966,"sc":1,"cc":1,"lpe":0.0,"lpr":155.85,"lq":12.85,"spr":170.0,"sq":17.79,"sb":5.78},{"ci":"2931","ri":"2932","ti":"2933","tc":"Москва","wi":10.17,"pi":"1482","mi":"E","v":1221634,"sc":14,"cc":13,"lpe":85.13,"lpr":112.53,"lq":36.66,"spr":107.22,"sq":41.65,"sb":0.01},{"ci":"2931","ri":"2932","ti":"422040","tc":"Рязань","wi":13.3,"pi":"1482","mi":"E","v":21348,"sc":2,"cc":2,"lpe":53.1,"lpr":158.92,"lq":35.35,"spr":135.92,"sq":41.9,"sb":0.0},{"ci":"2931","ri":"2932","ti":"2936","tc":"Ярославль","wi":3.97,"pi":"1482","mi":"E","v":269753,"sc":8,"cc":8,"lpe":64.18,"lpr":37.21,"lq":12.72,"spr":43.14,"sq":21.31,"sb":0.29},{"ci":"2931","ri":"2945","ti":"366652","tc":"Владикавказ","wi":1.65,"pi":"1482","mi":"E","v":7764,"sc":3,"cc":3,"lpe":86.27,"lpr":29.3,"lq":8.52,"spr":41.06,"sq":16.7,"sb":0.37},{"ci":"2931","ri":"2945","ti":"2947","tc":"Волгоград","wi":4.02,"pi":"1482","mi":"D","v":112636,"sc":6,"cc":6,"lpe":18.15,"lpr":79.46,"lq":2.57,"spr":128.47,"sq":43.15,"sb":0.0},{"ci":"2931","ri":"2945","ti":"352279","tc":"Грозный","wi":3.9,"pi":"1482","mi":"E","v":12768,"sc":2,"cc":2,"lpe":58.49,"lpr":37.44,"lq":11.96,"spr":32.35,"sq":15.2,"sb":0.41},{"ci":"2931","ri":"2945","ti":"2948","tc":"Краснодар","wi":1.94,"pi":"1482","mi":"E","v":343030,"sc":7,"cc":7,"lpe":97.84,"lpr":26.85,"lq":1.0,"spr":26.64,"sq":1.45,"sb":0.04},{"ci":"2931","ri":"2945","ti":"422506","tc":"Махачкала","wi":1.69,"pi":"1482","mi":"E","v":15556,"sc":3,"cc":3,"lpe":67.15,"lpr":16.04,"lq":5.33,"spr":20.61,"sq":10.18,"sb":0.34},{"ci":"2931","ri":"2945","ti":"2949","tc":"Новороссийск","wi":4.23,"pi":"1482","mi":"E","v":33523,"sc":3,"cc":3,"lpe":96.09,"lpr":46.02,"lq":1.0,"spr":47.64,"sq":1.39,"sb":0.0},{"ci":"2931","ri":"2945","ti":"2946","tc":"Ростов-на-Дону","wi":3.13,"pi":"1482","mi":"E","v":95047,"sc":10,"cc":9,"lpe":86.31,"lpr":66.9,"lq":9.25,"spr":63.99,"sq":11.03,"sb":0.16},{"ci":"2931","ri":"2945","ti":"5033","tc":"Сочи","wi":2.79,"pi":"1482","mi":"E","v":28714,"sc":2,"cc":2,"lpe":94.12,"lpr":131.23,"lq":1.0,"spr":131.34,"sq":1.66,"sb":0.0},{"ci":"2931","ri":"2945","ti":"423001","tc":"Таганрог","wi":9.77,"pi":"1482","mi":"","v":41064,"sc":0,"cc":0,"lpe":100.0,"lpr":192.22,"lq":1.0,"spr":192.22,"sq":1.0,"sb":0.0},{"ci":"310392","ri":"310393","ti":"310397","tc":"Андижан","wi":4.19,"pi":"1482","mi":"E","v":58335,"sc":1,"cc":1,"lpe":74.06,"lpr":87.39,"lq":7.78,"spr":77.69,"sq":9.02,"sb":0.0},{"ci":"310392","ri":"310393","ti":"310399","tc":"Бухара","wi":4.19,"pi":"1482","mi":"E","v":294391,"sc":4,"cc":4,"lpe":82.17,"lpr":23.2,"lq":7.33,"spr":29.25,"sq":12.26,"sb":0.12},{"ci":"310392","ri":"310393","ti":"422512","tc":"Коканд","wi":4.56,"pi":"1482","mi":"E","v":20411,"sc":1,"cc":1,"lpe":75.5,"lpr":82.72,"lq":3.71,"spr":106.55,"sq":8.38,"sb":0.0},{"ci":"310392","ri":"310393","ti":"310395","tc":"Наманган","wi":13.11,"pi":"1482","mi":"E","v":32045,"sc":2,"cc":2,"lpe":87.52,"lpr":275.56,"lq":17.72,"spr":286.72,"sq":26.63,"sb":0.0},{"ci":"310392","ri":"310393","ti":"310400","tc":"Нукус","wi":3.38,"pi":"1482","mi":"E","v":1162043,"sc":6,"cc":6,"lpe":90.96,"lpr":30.03,"lq":1.0,"spr":33.27,"sq":1.96,"sb":0.07},{"ci":"310392","ri":"310393","ti":"310396","tc":"Самарканд","wi":14.07,"pi":"1482","mi":"E","v":35937,"sc":3,"cc":3,"lpe":82.1,"lpr":1044.25,"lq":2.48,"spr":931.24,"sq":15.11,"sb":0.17},{"ci":"310392","ri":"310393","ti":"310394","tc":"Ташкент","wi":16.66,"pi":"1482","mi":"D","v":250123,"sc":4,"cc":4,"lpe":46.07,"lpr":242.01,"lq":64.21,"spr":221.62,"sq":73.64,"sb":0.38},{"ci":"310392","ri":"310393","ti":"310398","tc":"Фергана","wi":14.45,"pi":"1482","mi":"E","v":21672,"sc":2,"cc":2,"lpe":67.7,"lpr":250.22,"lq":44.23,"spr":295.83,"sq":51.7,"sb":0.69},{"ci":"3010","ri":"3011","ti":"422996","tc":"Белая Церковь","wi":9.42,"pi":"1482","mi":"E","v":31015,"sc":1,"cc":1,"lpe":94.68,"lpr":210.82,"lq":1.0,"spr":212.91,"sq":6.54,"sb":0.0},{"ci":"3010","ri":"3011","ti":"3014","tc":"Днепропетровск","wi":10.25,"pi":"1482","mi":"D","v":57306,"sc":13,"cc":11,"lpe":20.64,"lpr":544.97,"lq":2.79,"spr":1045.83,"sq":60.19,"sb":0.04},{"ci":"3010","ri":"3011","ti":"3015","tc":"Донецк","wi":13.4,"pi":"1482","mi":"E","v":107161,"sc":8,"cc":8,"lpe":85.44,"lpr":117.5,"lq":36.76,"spr":135.95,"sq":40.64,"sb":0.0},{"ci":"3010","ri":"3011","ti":"3016","tc":"Запорожье","wi":11.3,"pi":"1482","mi":"E","v":62778,"sc":7,"cc":7,"lpe":63.37,"lpr":150.08,"lq":20.63,"spr":207.58,"sq":32.84,"sb":0.1},{"ci":"3010","ri":"3011","ti":"3012","tc":"Киев","wi":11.05,"pi":"1482","mi":"E","v":221948,"sc":12,"cc":12,"lpe":55.52,"lpr":186.62,"lq":59.16,"spr":232.32,"sq":71.88,"sb":0.02},{"ci":"3010","ri":"3011","ti":"3017","tc":"Луганск","wi":2.68,"pi":"1482","mi":"E","v":122690,"sc":1,"cc":1,"lpe":91.85,"lpr":38.46,"lq":9.57,"spr":36.95,"sq":13.24,"sb":0.16},{"ci":"3010","ri":"3011","ti":"422998","tc":"Никополь","wi":4.95,"pi":"1482","mi":"E","v":13333,"sc":1,"cc":1,"lpe":95.54,"lpr":124.28,"lq":1.0,"spr":127.66,"sq":5.64,"sb":0.0},{"ci":"3010","ri":"3011","ti":"13055","tc":"Полтава","wi":19.71,"pi":"1482","mi":"E","v":30532,"sc":5,"cc":5,"lpe":61.1,"lpr":168.68,"lq":48.96,"spr":263.23,"sq":57.63,"sb":0.16},{"ci":"3010","ri":"3011","ti":"3013","tc":"Харьков","wi":9.65,"pi":"1482","mi":"E","v":99827,"sc":6,"cc":6,"lpe":71.03,"lpr":119.24,"lq":34.54,"spr":126.19,"sq":51.96,"sb":0.01},{"ci":"3010","ri":"3018","ti":"3022","tc":"Винница","wi":3.9,"pi":"1482","mi":"E","v":138827,"sc":2,"cc":2,"lpe":88.37,"lpr":38.57,"lq":9.13,"spr":40.9,"sq":9.6,"sb":0.26},{"ci":"3010","ri":"3018","ti":"3021","tc":"Житомир","wi":3.3,"pi":"1482","mi":"D","v":50731,"sc":4,"cc":3,"lpe":48.35,"lpr":10.11,"lq":3.96,"spr":22.98,"sq":27.94,"sb":1.14},{"ci":"3010","ri":"3018","ti":"3020","tc":"Ивано-Франковск","wi":2.69,"pi":"1482","mi":"","v":43499,"sc":0,"cc":0,"lpe":100.0,"lpr":19.27,"lq":1.0,"spr":19.27,"sq":1.0,"sb":0.0},{"ci":"3010","ri":"3018","ti":"3019","tc":"Львов","wi":10.44,"pi":"1482","mi":"C","v":99655,"sc":5,"cc":5,"lpe":0.0,"lpr":49.63,"lq":38.32,"spr":100.95,"sq":58.76,"sb":0.0},{"ci":"3010","ri":"3023","ti":"3025","tc":"Николаев","wi":13.29,"pi":"1482","mi":"B","v":42570,"sc":5,"cc":5,"lpe":0.0,"lpr":44.28,"lq":42.58,"spr":140.03,"sq":71.86,"sb":0.01},{"ci":"3010","ri":"3023","ti":"3024","tc":"Одесса","wi":16.57,"pi":"1482","mi":"C","v":97160,"sc":7,"cc":5,"lpe":0.0,"lpr":343.42,"lq":60.44,"spr":185.0,"sq":87.42,"sb":0.15},{"ci":"3010","ri":"3023","ti":"3028","tc":"Севастополь","wi":3.96,"pi":"1482","mi":"E","v":54825,"sc":4,"cc":4,"lpe":66.6,"lpr":19.86,"lq":11.56,"spr":35.83,"sq":18.86,"sb":0.05},{"ci":"3010","ri":"3023","ti":"3026","tc":"Симферополь","wi":10.7,"pi":"1482","mi":"E","v":21904,"sc":2,"cc":2,"lpe":98.91,"lpr":464.54,"lq":1.0,"spr":459.89,"sq":1.27,"sb":0.0},{"ci":"3010","ri":"3023","ti":"3027","tc":"Херсон","wi":3.62,"pi":"1482","mi":"E","v":37458,"sc":3,"cc":3,"lpe":63.67,"lpr":31.65,"lq":10.97,"spr":35.71,"sq":15.7,"sb":0.0},{"ci":"3010","ri":"3023","ti":"422089","tc":"Ялта","wi":11.97,"pi":"1482","mi":"E","v":5050,"sc":3,"cc":3,"lpe":70.97,"lpr":191.58,"lq":16.42,"spr":337.8,"sq":19.08,"sb":0.0},{"ci":"301309","ri":"301310","ti":"422978","tc":"Вантаа","wi":30.92,"pi":"1482","mi":"","v":25645,"sc":0,"cc":0,"lpe":100.0,"lpr":625.56,"lq":1.0,"spr":625.56,"sq":1.0,"sb":0.0},{"ci":"301309","ri":"301310","ti":"301315","tc":"Рованиеми","wi":26.7,"pi":"1482","mi":"D","v":5153,"sc":1,"cc":1,"lpe":18.49,"lpr":467.44,"lq":45.44,"spr":412.47,"sq":60.82,"sb":1.33},{"ci":"301309","ri":"301310","ti":"301313","tc":"Тампере","wi":28.77,"pi":"1482","mi":"D","v":24558,"sc":6,"cc":4,"lpe":0.0,"lpr":269.23,"lq":49.49,"spr":221.9,"sq":65.21,"sb":1.3},{"ci":"301309","ri":"301310","ti":"301314","tc":"Турку","wi":45.94,"pi":"1482","mi":"D","v":13661,"sc":2,"cc":2,"lpe":34.11,"lpr":386.72,"lq":50.2,"spr":329.59,"sq":59.5,"sb":1.08},{"ci":"301309","ri":"301310","ti":"301311","tc":"Хельсинки","wi":45.51,"pi":"1482","mi":"D","v":61050,"sc":9,"cc":8,"lpe":32.16,"lpr":576.03,"lq":51.52,"spr":472.63,"sq":63.79,"sb":1.01},{"ci":"301309","ri":"301310","ti":"301312","tc":"Эспоо","wi":34.24,"pi":"1482","mi":"D","v":30983,"sc":2,"cc":1,"lpe":48.36,"lpr":331.71,"lq":51.85,"spr":294.68,"sq":58.28,"sb":0.84},{"ci":"15906","ri":"3030","ti":"3037","tc":"Бордо","wi":28.61,"pi":"1482","mi":"A","v":26305,"sc":3,"cc":3,"lpe":0.0,"lpr":267.67,"lq":78.14,"spr":463.29,"sq":100.15,"sb":0.23},{"ci":"15906","ri":"3030","ti":"3039","tc":"Гавр","wi":21.16,"pi":"1482","mi":"AA","v":22220,"sc":2,"cc":2,"lpe":0.0,"lpr":873.8,"lq":41.5,"spr":675.92,"sq":118.16,"sb":3.13},{"ci":"15906","ri":"3030","ti":"422528","tc":"Канны","wi":38.92,"pi":"1482","mi":"A","v":12659,"sc":3,"cc":3,"lpe":0.0,"lpr":225.96,"lq":35.29,"spr":473.5,"sq":100.38,"sb":0.36},{"ci":"15906","ri":"3030","ti":"3033","tc":"Лион","wi":24.75,"pi":"1482","mi":"A","v":53049,"sc":2,"cc":2,"lpe":0.0,"lpr":249.63,"lq":80.05,"spr":654.94,"sq":111.65,"sb":2.85},{"ci":"15906","ri":"3030","ti":"3032","tc":"Марсель","wi":28.94,"pi":"1482","mi":"A","v":78467,"sc":2,"cc":1,"lpe":0.0,"lpr":230.27,"lq":88.46,"spr":800.0,"sq":129.01,"sb":4.83},{"ci":"15906","ri":"3030","ti":"3041","tc":"Нант","wi":22.15,"pi":"1482","mi":"B","v":15014,"sc":2,"cc":2,"lpe":0.0,"lpr":244.9,"lq":83.12,"spr":799.91,"sq":129.0,"sb":4.83},{"ci":"15906","ri":"3030","ti":"3035","tc":"Ницца","wi":19.84,"pi":"1482","mi":"B","v":34852,"sc":3,"cc":3,"lpe":0.0,"lpr":190.43,"lq":82.32,"spr":511.74,"sq":109.98,"sb":2.05},{"ci":"15906","ri":"3030","ti":"3031","tc":"Париж","wi":29.59,"pi":"1482","mi":"A","v":231204,"sc":6,"cc":4,"lpe":0.0,"lpr":211.15,"lq":86.56,"spr":756.83,"sq":125.32,"sb":4.3},{"ci":"15906","ri":"3030","ti":"3040","tc":"Реймс","wi":20.27,"pi":"1482","mi":"B","v":19181,"sc":2,"cc":2,"lpe":0.0,"lpr":165.03,"lq":63.58,"spr":441.46,"sq":99.06,"sb":0.06},{"ci":"15906","ri":"3030","ti":"3038","tc":"Ренн","wi":22.73,"pi":"1482","mi":"A","v":15413,"sc":2,"cc":2,"lpe":0.0,"lpr":202.68,"lq":47.71,"spr":394.39,"sq":99.71,"sb":0.21},{"ci":"15906","ri":"3030","ti":"3036","tc":"Страсбург","wi":28.84,"pi":"1482","mi":"A","v":45862,"sc":5,"cc":4,"lpe":0.0,"lpr":237.05,"lq":71.6,"spr":501.27,"sq":107.1,"sb":1.39},{"ci":"15906","ri":"3030","ti":"422018","tc":"Таланс","wi":17.52,"pi":"1482","mi":"B","v":5683,"sc":3,"cc":3,"lpe":0.0,"lpr":125.05,"lq":61.15,"spr":224.07,"sq":88.79,"sb":0.01},{"ci":"15906","ri":"3030","ti":"3034","tc":"Тулуза","wi":20.95,"pi":"1482","mi":"D","v":33655,"sc":3,"cc":3,"lpe":18.12,"lpr":216.04,"lq":78.74,"spr":602.55,"sq":111.61,"sb":2.83},{"ci":"325655","ri":"325656","ti":"325659","tc":"Нарва","wi":14.26,"pi":"1482","mi":"D","v":13367,"sc":3,"cc":3,"lpe":33.71,"lpr":197.63,"lq":40.51,"spr":255.49,"sq":61.1,"sb":1.68},{"ci":"325655","ri":"325656","ti":"422019","tc":"Пярну","wi":9.11,"pi":"1482","mi":"E","v":8135,"sc":3,"cc":3,"lpe":81.51,"lpr":230.84,"lq":1.39,"spr":217.47,"sq":3.41,"sb":0.14},{"ci":"325655","ri":"325656","ti":"325657","tc":"Таллин","wi":26.96,"pi":"1482","mi":"E","v":24853,"sc":3,"cc":3,"lpe":88.58,"lpr":3055.53,"lq":4.55,"spr":2768.24,"sq":14.04,"sb":0.06},{"ci":"325655","ri":"325656","ti":"325658","tc":"Тарту","wi":16.35,"pi":"1482","mi":"E","v":9470,"sc":3,"cc":3,"lpe":94.5,"lpr":474.01,"lq":4.66,"spr":466.3,"sq":5.12,"sb":0.09}]